Workbook

Sheet Amazon Weekly Sales Rpt 
A1: IDENTIFYING INFO | AL1: On Order Info | AM1: On Order Info
A2: Dealer Name | B2: Month Ending | D2: UPC | E2: FBM Specific Combo | F2: FBA Specific Combo | G2: ASIN | H2: FBM Only vs FBA Designations | I2: Style # | J2: Description | K2: Color | L2: Size | M2: GoBros List Price | N2: FBA List Price | O2: GoBros COG (Includes Earned 10% Discount) | P2: Lowest Price on AMZ Difference | R2: GB Units Sold | S2: GB $$ Volume | U2: FBM Units Sold | V2: FBM $$ Volume | W2: Sessions | X2: Featured Offer (Buy Box) Percentage | Z2: FBA Units Sold | AA2: FBA $$ Volume | AB2: Sessions | AC2: Featured Offer (Buy Box) Percentage | AE2: Fulfillable Units FBM | AF2: Fulfillable FBA | AG2: Inbound FBA | AH2: Processing FBA | AI2: TOTAL at FBA | AJ2: TOTAL BY UNITS (FBM and FBA) | AK2: Current Holdings Inventory Value | AL2: FBA 5.14ZZ, Backorders, Listing Issues | AM2: GB/FBM (12.9 GB and Backorders)
A3: GoBros | B3: 46173 | D3: 048323011686 | E3: WIGF1019_051_wht_0 | F3: ZZWIGF1019_051_wht_0M | G3: #N/A | H3: FBM Only | I3: F1019 | J3: Wigwam 7-Footer Extra Tall Socks | K3: White | L3: One Size Fits Most | O3: 6.48 | R3: =IFERROR(VLOOKUP(E3,Sheet6!$A$2:$B$500,2,FALSE),0) -> 7 | S3: =IFERROR(VLOOKUP(E3,Sheet6!$C$2:$D$35017,2,FALSE),0) -> 105 | U3: =IFERROR(VLOOKUP(E3,Sheet2!$AA$1:$AB$975,2,FALSE),0) -> 5 | V3: =IFERROR(VLOOKUP(E3,Sheet2!$AC$1:$AD$975,2,FALSE),0) -> 74.95 | W3: =IFERROR(VLOOKUP(E3,Sheet2!$AE$1:$AF$975,2,FALSE),0) -> 86 | X3: =IFERROR(VLOOKUP(E3,Sheet2!$AG$1:$AH$975,2,FALSE),0) -> 0.1339 | Z3: =IFERROR(VLOOKUP(F3,Sheet2!$AA$1:$AB$975,2,FALSE),0) -> 0 | AA3: =IFERROR(VLOOKUP(F3,Sheet2!$AC$1:$AD$975,2,FALSE),0) -> 0 | AB3: =IFERROR(VLOOKUP(F3,Sheet2!$AE$2:$AF$6539,2,FALSE),0) -> 0 | AC3: =IFERROR(VLOOKUP(F3,Sheet2!$AG$2:$AH$6539,2,FALSE),0) -> 0 | AE3: 188 | AF3: 0 | AG3: 0 | AH3: 0 | AI3: 0 | AJ3: =SUM(AE3+AI3) -> 188 | AK3: =SUM(AJ3*O3) -> 1218.24 | AL3: 0 | AM3: 0
A4: GoBros | B4: 46173 | D4: 048323013185 | E4: WIGF1054_051_whi_1 | F4: ZZWIGF1054_051_whi_1 | G4: #N/A | H4: FBM Only | I4: F1054 | J4: Wigwam Volley Midweight Crew Socks | K4: White | L4: Medium | O4: 5.85 | R4: =IFERROR(VLOOKUP(E4,Sheet6!$A$2:$B$500,2,FALSE),0) -> 0 | S4: =IFERROR(VLOOKUP(E4,Sheet6!$C$2:$D$35017,2,FALSE),0) -> 0 | U4: =IFERROR(VLOOKUP(E4,Sheet2!$AA$1:$AB$975,2,FALSE),0) -> 5 | V4: =IFERROR(VLOOKUP(E4,Sheet2!$AC$1:$AD$975,2,FALSE),0) -> 65 | W4: =IFERROR(VLOOKUP(E4,Sheet2!$AE$1:$AF$975,2,FALSE),0) -> 7 | X4: =IFERROR(VLOOKUP(E4,Sheet2!$AG$1:$AH$975,2,FALSE),0) -> 1 | Z4: =IFERROR(VLOOKUP(F4,Sheet2!$AA$1:$AB$975,2,FALSE),0) -> 0 | AA4: =IFERROR(VLOOKUP(F4,Sheet2!$AC$1:$AD$975,2,FALSE),0) -> 0 | AB4: =IFERROR(VLOOKUP(F4,Sheet2!$AE$2:$AF$6539,2,FALSE),0) -> 0 | AC4: =IFERROR(VLOOKUP(F4,Sheet2!$AG$2:$AH$6539,2,FALSE),0) -> 0 | AE4: 3 | AF4: 0 | AG4: 0 | AH4: 0 | AI4: 0 | AJ4: =SUM(AE4+AI4) -> 3 | AK4: =SUM(AJ4*O4) -> 17.55 | AL4: 0 | AM4: 0
A5: GoBros | B5: 46173 | D5: 048323013178 | E5: WIGF1054_051_whi_2 | F5: ZZWIGF1054_051_whi_2 | G5: #N/A | H5: FBM Only | I5: F1054 | J5: Wigwam Volley Midweight Crew Socks | K5: White | L5: Large | O5: 5.85 | R5: =IFERROR(VLOOKUP(E5,Sheet6!$A$2:$B$500,2,FALSE),0) -> 0 | S5: =IFERROR(VLOOKUP(E5,Sheet6!$C$2:$D$35017,2,FALSE),0) -> 0 | U5: =IFERROR(VLOOKUP(E5,Sheet2!$AA$1:$AB$975,2,FALSE),0) -> 0 | V5: =IFERROR(VLOOKUP(E5,Sheet2!$AC$1:$AD$975,2,FALSE),0) -> 0 | W5: =IFERROR(VLOOKUP(E5,Sheet2!$AE$1:$AF$975,2,FALSE),0) -> 0 | X5: =IFERROR(VLOOKUP(E5,Sheet2!$AG$1:$AH$975,2,FALSE),0) -> 0 | Z5: =IFERROR(VLOOKUP(F5,Sheet2!$AA$1:$AB$975,2,FALSE),0) -> 0 | AA5: =IFERROR(VLOOKUP(F5,Sheet2!$AC$1:$AD$975,2,FALSE),0) -> 0 | AB5: =IFERROR(VLOOKUP(F5,Sheet2!$AE$2:$AF$6539,2,FALSE),0) -> 0 | AC5: =IFERROR(VLOOKUP(F5,Sheet2!$AG$2:$AH$6539,2,FALSE),0) -> 0 | AE5: 3 | AF5: 0 | AG5: 0 | AH5: 0 | AI5: 0 | AJ5: =SUM(AE5+AI5) -> 3 | AK5: =SUM(AJ5*O5) -> 17.55 | AL5: 0 | AM5: 0
A6: GoBros | B6: 46173 | D6: 048323013192 | E6: WIGF1054_051_whi_3 | F6: ZZWIGF1054_051_whi_3 | G6: #N/A | H6: FBM Only | I6: F1054 | J6: Wigwam Volley Midweight Crew Socks | K6: White | L6: X-Large | O6: 5.85 | R6: =IFERROR(VLOOKUP(E6,Sheet6!$A$2:$B$500,2,FALSE),0) -> 0 | S6: =IFERROR(VLOOKUP(E6,Sheet6!$C$2:$D$35017,2,FALSE),0) -> 0 | U6: =IFERROR(VLOOKUP(E6,Sheet2!$AA$1:$AB$975,2,FALSE),0) -> 0 | V6: =IFERROR(VLOOKUP(E6,Sheet2!$AC$1:$AD$975,2,FALSE),0) -> 0 | W6: =IFERROR(VLOOKUP(E6,Sheet2!$AE$1:$AF$975,2,FALSE),0) -> 0 | X6: =IFERROR(VLOOKUP(E6,Sheet2!$AG$1:$AH$975,2,FALSE),0) -> 0 | Z6: =IFERROR(VLOOKUP(F6,Sheet2!$AA$1:$AB$975,2,FALSE),0) -> 0 | AA6: =IFERROR(VLOOKUP(F6,Sheet2!$AC$1:$AD$975,2,FALSE),0) -> 0 | AB6: =IFERROR(VLOOKUP(F6,Sheet2!$AE$2:$AF$6539,2,FALSE),0) -> 0 | AC6: =IFERROR(VLOOKUP(F6,Sheet2!$AG$2:$AH$6539,2,FALSE),0) -> 0 | AE6: 26 | AF6: 0 | AG6: 0 | AH6: 0 | AI6: 0 | AJ6: =SUM(AE6+AI6) -> 26 | AK6: =SUM(AJ6*O6) -> 152.1 | AL6: 0 | AM6: 0
A7: GoBros | B7: 46173 | D7: 048323013208 | E7: WIGF1054_051_whi_4 | F7: ZZWIGF1054_051_whi_4 | G7: #N/A | H7: FBM Only | I7: F1054 | J7: Wigwam Volley Midweight Crew Socks | K7: White | L7: XX-Large | O7: 5.85 | R7: =IFERROR(VLOOKUP(E7,Sheet6!$A$2:$B$500,2,FALSE),0) -> 0 | S7: =IFERROR(VLOOKUP(E7,Sheet6!$C$2:$D$35017,2,FALSE),0) -> 0 | U7: =IFERROR(VLOOKUP(E7,Sheet2!$AA$1:$AB$975,2,FALSE),0) -> 0 | V7: =IFERROR(VLOOKUP(E7,Sheet2!$AC$1:$AD$975,2,FALSE),0) -> 0 | W7: =IFERROR(VLOOKUP(E7,Sheet2!$AE$1:$AF$975,2,FALSE),0) -> 0 | X7: =IFERROR(VLOOKUP(E7,Sheet2!$AG$1:$AH$975,2,FALSE),0) -> 0 | Z7: =IFERROR(VLOOKUP(F7,Sheet2!$AA$1:$AB$975,2,FALSE),0) -> 0 | AA7: =IFERROR(VLOOKUP(F7,Sheet2!$AC$1:$AD$975,2,FALSE),0) -> 0 | AB7: =IFERROR(VLOOKUP(F7,Sheet2!$AE$2:$AF$6539,2,FALSE),0) -> 0 | AC7: =IFERROR(VLOOKUP(F7,Sheet2!$AG$2:$AH$6539,2,FALSE),0) -> 0 | AE7: 13 | AF7: 0 | AG7: 0 | AH7: 0 | AI7: 0 | AJ7: =SUM(AE7+AI7) -> 13 | AK7: =SUM(AJ7*O7) -> 76.05 | AL7: 0 | AM7: 0
A8: GoBros | B8: 46173 | D8: 048323434096 | E8: WIGF1054_052_bla_1 | F8: ZZWIGF1054_052_bla_1 | G8: #N/A | H8: FBM Only | I8: F1054 | J8: Wigwam Volley Midweight Crew Socks | K8: Black | L8: Medium | O8: 5.85 | R8: =IFERROR(VLOOKUP(E8,Sheet6!$A$2:$B$500,2,FALSE),0) -> 0 | S8: =IFERROR(VLOOKUP(E8,Sheet6!$C$2:$D$35017,2,FALSE),0) -> 0 | U8: =IFERROR(VLOOKUP(E8,Sheet2!$AA$1:$AB$975,2,FALSE),0) -> 0 | V8: =IFERROR(VLOOKUP(E8,Sheet2!$AC$1:$AD$975,2,FALSE),0) -> 0 | W8: =IFERROR(VLOOKUP(E8,Sheet2!$AE$1:$AF$975,2,FALSE),0) -> 0 | X8: =IFERROR(VLOOKUP(E8,Sheet2!$AG$1:$AH$975,2,FALSE),0) -> 0 | Z8: =IFERROR(VLOOKUP(F8,Sheet2!$AA$1:$AB$975,2,FALSE),0) -> 0 | AA8: =IFERROR(VLOOKUP(F8,Sheet2!$AC$1:$AD$975,2,FALSE),0) -> 0 | AB8: =IFERROR(VLOOKUP(F8,Sheet2!$AE$2:$AF$6539,2,FALSE),0) -> 0 | AC8: =IFERROR(VLOOKUP(F8,Sheet2!$AG$2:$AH$6539,2,FALSE),0) -> 0 | AE8: 0 | AF8: 0 | AG8: 0 | AH8: 0 | AI8: 0 | AJ8: =SUM(AE8+AI8) -> 0 | AK8: =SUM(AJ8*O8) -> 0 | AL8: 0 | AM8: 0
A9: GoBros | B9: 46173 | D9: 048323434102 | E9: WIGF1054_052_bla_2 | F9: ZZWIGF1054_052_bla_2 | G9: #N/A | H9: FBM Only | I9: F1054 | J9: Wigwam Volley Midweight Crew Socks | K9: Black | L9: Large | O9: 5.85 | R9: =IFERROR(VLOOKUP(E9,Sheet6!$A$2:$B$500,2,FALSE),0) -> 0 | S9: =IFERROR(VLOOKUP(E9,Sheet6!$C$2:$D$35017,2,FALSE),0) -> 0 | U9: =IFERROR(VLOOKUP(E9,Sheet2!$AA$1:$AB$975,2,FALSE),0) -> 3 | V9: =IFERROR(VLOOKUP(E9,Sheet2!$AC$1:$AD$975,2,FALSE),0) -> 39 | W9: =IFERROR(VLOOKUP(E9,Sheet2!$AE$1:$AF$975,2,FALSE),0) -> 11 | X9: =IFERROR(VLOOKUP(E9,Sheet2!$AG$1:$AH$975,2,FALSE),0) -> 1 | Z9: =IFERROR(VLOOKUP(F9,Sheet2!$AA$1:$AB$975,2,FALSE),0) -> 0 | AA9: =IFERROR(VLOOKUP(F9,Sheet2!$AC$1:$AD$975,2,FALSE),0) -> 0 | AB9: =IFERROR(VLOOKUP(F9,Sheet2!$AE$2:$AF$6539,2,FALSE),0) -> 0 | AC9: =IFERROR(VLOOKUP(F9,Sheet2!$AG$2:$AH$6539,2,FALSE),0) -> 0 | AE9: 6 | AF9: 0 | AG9: 0 | AH9: 0 | AI9: 0 | AJ9: =SUM(AE9+AI9) -> 6 | AK9: =SUM(AJ9*O9) -> 35.1 | AL9: 0 | AM9: 0
A10: GoBros | B10: 46173 | D10: 048323434119 | E10: WIGF1054_052_bla_3 | F10: ZZWIGF1054_052_bla_3 | G10: #N/A | H10: FBM Only | I10: F1054 | J10: Wigwam Volley Midweight Crew Socks | K10: Black | L10: X-Large | O10: 5.85 | R10: =IFERROR(VLOOKUP(E10,Sheet6!$A$2:$B$500,2,FALSE),0) -> 3 | S10: =IFERROR(VLOOKUP(E10,Sheet6!$C$2:$D$35017,2,FALSE),0) -> 39 | U10: =IFERROR(VLOOKUP(E10,Sheet2!$AA$1:$AB$975,2,FALSE),0) -> 1 | V10: =IFERROR(VLOOKUP(E10,Sheet2!$AC$1:$AD$975,2,FALSE),0) -> 13 | W10: =IFERROR(VLOOKUP(E10,Sheet2!$AE$1:$AF$975,2,FALSE),0) -> 2 | X10: =IFERROR(VLOOKUP(E10,Sheet2!$AG$1:$AH$975,2,FALSE),0) -> 1 | Z10: =IFERROR(VLOOKUP(F10,Sheet2!$AA$1:$AB$975,2,FALSE),0) -> 0 | AA10: =IFERROR(VLOOKUP(F10,Sheet2!$AC$1:$AD$975,2,FALSE),0) -> 0 | AB10: =IFERROR(VLOOKUP(F10,Sheet2!$AE$2:$AF$6539,2,FALSE),0) -> 0 | AC10: =IFERROR(VLOOKUP(F10,Sheet2!$AG$2:$AH$6539,2,FALSE),0) -> 0 | AE10: 7 | AF10: 0 | AG10: 0 | AH10: 0 | AI10: 0 | AJ10: =SUM(AE10+AI10) -> 7 | AK10: =SUM(AJ10*O10) -> 40.95 | AL10: 0 | AM10: 0
A11: GoBros | B11: 46173 | D11: 048323013437 | E11: WIGF1055_051_wht_0 | F11: ZZWIGF1055_051_wht_0 | G11: #N/A | H11: FBM Only | I11: F1055 | J11: Wigwam King Cotton Heavyweight Crew Socks | K11: White | L11: Medium | O11: 6.48 | R11: =IFERROR(VLOOKUP(E11,Sheet6!$A$2:$B$500,2,FALSE),0) -> 0 | S11: =IFERROR(VLOOKUP(E11,Sheet6!$C$2:$D$35017,2,FALSE),0) -> 0 | U11: =IFERROR(VLOOKUP(E11,Sheet2!$AA$1:$AB$975,2,FALSE),0) -> 0 | V11: =IFERROR(VLOOKUP(E11,Sheet2!$AC$1:$AD$975,2,FALSE),0) -> 0 | W11: =IFERROR(VLOOKUP(E11,Sheet2!$AE$1:$AF$975,2,FALSE),0) -> 0 | X11: =IFERROR(VLOOKUP(E11,Sheet2!$AG$1:$AH$975,2,FALSE),0) -> 0 | Z11: =IFERROR(VLOOKUP(F11,Sheet2!$AA$1:$AB$975,2,FALSE),0) -> 0 | AA11: =IFERROR(VLOOKUP(F11,Sheet2!$AC$1:$AD$975,2,FALSE),0) -> 0 | AB11: =IFERROR(VLOOKUP(F11,Sheet2!$AE$2:$AF$6539,2,FALSE),0) -> 0 | AC11: =IFERROR(VLOOKUP(F11,Sheet2!$AG$2:$AH$6539,2,FALSE),0) -> 0 | AE11: 0 | AF11: 0 | AG11: 0 | AH11: 0 | AI11: 0 | AJ11: =SUM(AE11+AI11) -> 0 | AK11: =SUM(AJ11*O11) -> 0 | AL11: 0 | AM11: 0
A12: GoBros | B12: 46173 | D12: 048323013420 | E12: WIGF1055_051_wht_1 | F12: ZZWIGF1055_051_wht_1 | G12: #N/A | H12: FBM Only | I12: F1055 | J12: Wigwam King Cotton Heavyweight Crew Socks | K12: White | L12: Large | O12: 6.48 | R12: =IFERROR(VLOOKUP(E12,Sheet6!$A$2:$B$500,2,FALSE),0) -> 12 | S12: =IFERROR(VLOOKUP(E12,Sheet6!$C$2:$D$35017,2,FALSE),0) -> 180 | U12: =IFERROR(VLOOKUP(E12,Sheet2!$AA$1:$AB$975,2,FALSE),0) -> 87 | V12: =IFERROR(VLOOKUP(E12,Sheet2!$AC$1:$AD$975,2,FALSE),0) -> 1304.13 | W12: =IFERROR(VLOOKUP(E12,Sheet2!$AE$1:$AF$975,2,FALSE),0) -> 271 | X12: =IFERROR(VLOOKUP(E12,Sheet2!$AG$1:$AH$975,2,FALSE),0) -> 1 | Z12: =IFERROR(VLOOKUP(F12,Sheet2!$AA$1:$AB$975,2,FALSE),0) -> 0 | AA12: =IFERROR(VLOOKUP(F12,Sheet2!$AC$1:$AD$975,2,FALSE),0) -> 0 | AB12: =IFERROR(VLOOKUP(F12,Sheet2!$AE$2:$AF$6539,2,FALSE),0) -> 0 | AC12: =IFERROR(VLOOKUP(F12,Sheet2!$AG$2:$AH$6539,2,FALSE),0) -> 0 | AE12: 68 | AF12: 0 | AG12: 0 | AH12: 0 | AI12: 0 | AJ12: =SUM(AE12+AI12) -> 68 | AK12: =SUM(AJ12*O12) -> 440.64 | AL12: 0 | AM12: 12
A13: GoBros | B13: 46173 | D13: 048323013444 | E13: WIGF1055_051_wht_2 | F13: ZZWIGF1055_051_wht_2 | G13: #N/A | H13: FBM Only | I13: F1055 | J13: Wigwam King Cotton Heavyweight Crew Socks | K13: White | L13: X-Large | O13: 6.48 | R13: =IFERROR(VLOOKUP(E13,Sheet6!$A$2:$B$500,2,FALSE),0) -> 8 | S13: =IFERROR(VLOOKUP(E13,Sheet6!$C$2:$D$35017,2,FALSE),0) -> 117.75 | U13: =IFERROR(VLOOKUP(E13,Sheet2!$AA$1:$AB$975,2,FALSE),0) -> 46 | V13: =IFERROR(VLOOKUP(E13,Sheet2!$AC$1:$AD$975,2,FALSE),0) -> 690 | W13: =IFERROR(VLOOKUP(E13,Sheet2!$AE$1:$AF$975,2,FALSE),0) -> 131 | X13: =IFERROR(VLOOKUP(E13,Sheet2!$AG$1:$AH$975,2,FALSE),0) -> 1 | Z13: =IFERROR(VLOOKUP(F13,Sheet2!$AA$1:$AB$975,2,FALSE),0) -> 0 | AA13: =IFERROR(VLOOKUP(F13,Sheet2!$AC$1:$AD$975,2,FALSE),0) -> 0 | AB13: =IFERROR(VLOOKUP(F13,Sheet2!$AE$2:$AF$6539,2,FALSE),0) -> 0 | AC13: =IFERROR(VLOOKUP(F13,Sheet2!$AG$2:$AH$6539,2,FALSE),0) -> 0 | AE13: 251 | AF13: 0 | AG13: 0 | AH13: 0 | AI13: 0 | AJ13: =SUM(AE13+AI13) -> 251 | AK13: =SUM(AJ13*O13) -> 1626.48 | AL13: 0 | AM13: 0
A14: GoBros | B14: 46173 | D14: 048323485180 | E14: WIGF1055_052_blk_0 | F14: ZZWIGF1055_052_blk_0 | G14: #N/A | H14: FBM Only | I14: F1055 | J14: Wigwam King Cotton Heavyweight Crew Socks | K14: Black | L14: Medium | O14: 6.48 | R14: =IFERROR(VLOOKUP(E14,Sheet6!$A$2:$B$500,2,FALSE),0) -> 0 | S14: =IFERROR(VLOOKUP(E14,Sheet6!$C$2:$D$35017,2,FALSE),0) -> 0 | U14: =IFERROR(VLOOKUP(E14,Sheet2!$AA$1:$AB$975,2,FALSE),0) -> 0 | V14: =IFERROR(VLOOKUP(E14,Sheet2!$AC$1:$AD$975,2,FALSE),0) -> 0 | W14: =IFERROR(VLOOKUP(E14,Sheet2!$AE$1:$AF$975,2,FALSE),0) -> 0 | X14: =IFERROR(VLOOKUP(E14,Sheet2!$AG$1:$AH$975,2,FALSE),0) -> 0 | Z14: =IFERROR(VLOOKUP(F14,Sheet2!$AA$1:$AB$975,2,FALSE),0) -> 0 | AA14: =IFERROR(VLOOKUP(F14,Sheet2!$AC$1:$AD$975,2,FALSE),0) -> 0 | AB14: =IFERROR(VLOOKUP(F14,Sheet2!$AE$2:$AF$6539,2,FALSE),0) -> 0 | AC14: =IFERROR(VLOOKUP(F14,Sheet2!$AG$2:$AH$6539,2,FALSE),0) -> 0 | AE14: 28 | AF14: 0 | AG14: 0 | AH14: 0 | AI14: 0 | AJ14: =SUM(AE14+AI14) -> 28 | AK14: =SUM(AJ14*O14) -> 181.44 | AL14: 0 | AM14: 0
... A22: GoBros | B22: 46173 | D22: 048323013697 | E22: WIGF1057_51_whi_3 | F22: ZZWIGF1057_51_whi_3 | G22: #N/A | H22: FBM Only | I22: F1057 | J22: Wigwam King Cotton High Heavyweight Socks | K22: White | L22: X-Large | O22: 7.776 | R22: =IFERROR(VLOOKUP(E22,Sheet6!$A$2:$B$500,2,FALSE),0) -> 5 | S22: =IFERROR(VLOOKUP(E22,Sheet6!$C$2:$D$35017,2,FALSE),0) -> 90 | U22: =IFERROR(VLOOKUP(E22,Sheet2!$AA$1:$AB$975,2,FALSE),0) -> 0 | V22: =IFERROR(VLOOKUP(E22,Sheet2!$AC$1:$AD$975,2,FALSE),0) -> 0 | W22: =IFERROR(VLOOKUP(E22,Sheet2!$AE$1:$AF$975,2,FALSE),0) -> 0 | X22: =IFERROR(VLOOKUP(E22,Sheet2!$AG$1:$AH$975,2,FALSE),0) -> 0 | Z22: =IFERROR(VLOOKUP(F22,Sheet2!$AA$1:$AB$975,2,FALSE),0) -> 0 | AA22: =IFERROR(VLOOKUP(F22,Sheet2!$AC$1:$AD$975,2,FALSE),0) -> 0 | AB22: =IFERROR(VLOOKUP(F22,Sheet2!$AE$2:$AF$6539,2,FALSE),0) -> 0 | AC22: =IFERROR(VLOOKUP(F22,Sheet2!$AG$2:$AH$6539,2,FALSE),0) -> 0 | AE22: 35 | AF22: 0 | AG22: 0 | AH22: 0 | AI22: 0 | AJ22: =SUM(AE22+AI22) -> 35 | AK22: =SUM(AJ22*O22) -> 272.16 | AL22: 0 | AM22: 0
A23: GoBros | B23: 46173 | D23: 048323013796 | E23: WIGF1061_051_wht_0 | F23: ZZWIGF1061_051_wht_0 | G23: #N/A | H23: FBM Only | I23: F1061 | J23: Wigwam Master Lightweight Crew Socks | K23: White | L23: 10 | O23: 7.776 | R23: =IFERROR(VLOOKUP(E23,Sheet6!$A$2:$B$500,2,FALSE),0) -> 0 | S23: =IFERROR(VLOOKUP(E23,Sheet6!$C$2:$D$35017,2,FALSE),0) -> 0 | U23: =IFERROR(VLOOKUP(E23,Sheet2!$AA$1:$AB$975,2,FALSE),0) -> 0 | V23: =IFERROR(VLOOKUP(E23,Sheet2!$AC$1:$AD$975,2,FALSE),0) -> 0 | W23: =IFERROR(VLOOKUP(E23,Sheet2!$AE$1:$AF$975,2,FALSE),0) -> 0 | X23: =IFERROR(VLOOKUP(E23,Sheet2!$AG$1:$AH$975,2,FALSE),0) -> 0 | Z23: =IFERROR(VLOOKUP(F23,Sheet2!$AA$1:$AB$975,2,FALSE),0) -> 0 | AA23: =IFERROR(VLOOKUP(F23,Sheet2!$AC$1:$AD$975,2,FALSE),0) -> 0 | AB23: =IFERROR(VLOOKUP(F23,Sheet2!$AE$2:$AF$6539,2,FALSE),0) -> 0 | AC23: =IFERROR(VLOOKUP(F23,Sheet2!$AG$2:$AH$6539,2,FALSE),0) -> 0 | AE23: 70 | AF23: 0 | AG23: 6 | AH23: 0 | AI23: 6 | AJ23: =SUM(AE23+AI23) -> 76 | AK23: =SUM(AJ23*O23) -> 590.976 | AL23: 6 | AM23: 0
A24: GoBros | B24: 46173 | D24: 048323013802 | E24: WIGF1061_051_wht_1 | F24: ZZWIGF1061_051_wht_1 | G24: #N/A | H24: FBM Only | I24: F1061 | J24: Wigwam Master Lightweight Crew Socks | K24: White | L24: 11 | O24: 7.776 | R24: =IFERROR(VLOOKUP(E24,Sheet6!$A$2:$B$500,2,FALSE),0) -> 0 | S24: =IFERROR(VLOOKUP(E24,Sheet6!$C$2:$D$35017,2,FALSE),0) -> 0 | U24: =IFERROR(VLOOKUP(E24,Sheet2!$AA$1:$AB$975,2,FALSE),0) -> 0 | V24: =IFERROR(VLOOKUP(E24,Sheet2!$AC$1:$AD$975,2,FALSE),0) -> 0 | W24: =IFERROR(VLOOKUP(E24,Sheet2!$AE$1:$AF$975,2,FALSE),0) -> 0 | X24: =IFERROR(VLOOKUP(E24,Sheet2!$AG$1:$AH$975,2,FALSE),0) -> 0 | Z24: =IFERROR(VLOOKUP(F24,Sheet2!$AA$1:$AB$975,2,FALSE),0) -> 0 | AA24: =IFERROR(VLOOKUP(F24,Sheet2!$AC$1:$AD$975,2,FALSE),0) -> 0 | AB24: =IFERROR(VLOOKUP(F24,Sheet2!$AE$2:$AF$6539,2,FALSE),0) -> 0 | AC24: =IFERROR(VLOOKUP(F24,Sheet2!$AG$2:$AH$6539,2,FALSE),0) -> 0 | AE24: 66 | AF24: 0 | AG24: 0 | AH24: 0 | AI24: 0 | AJ24: =SUM(AE24+AI24) -> 66 | AK24: =SUM(AJ24*O24) -> 513.216 | AL24: 0 | AM24: 0
A25: GoBros | B25: 46173 | D25: 048323013819 | E25: WIGF1061_051_wht_2 | F25: ZZWIGF1061_051_wht_2 | G25: #N/A | H25: FBM Only | I25: F1061 | J25: Wigwam Master Lightweight Crew Socks | K25: White | L25: 12 | O25: 7.776 | R25: =IFERROR(VLOOKUP(E25,Sheet6!$A$2:$B$500,2,FALSE),0) -> 0 | S25: =IFERROR(VLOOKUP(E25,Sheet6!$C$2:$D$35017,2,FALSE),0) -> 0 | U25: =IFERROR(VLOOKUP(E25,Sheet2!$AA$1:$AB$975,2,FALSE),0) -> 0 | V25: =IFERROR(VLOOKUP(E25,Sheet2!$AC$1:$AD$975,2,FALSE),0) -> 0 | W25: =IFERROR(VLOOKUP(E25,Sheet2!$AE$1:$AF$975,2,FALSE),0) -> 0 | X25: =IFERROR(VLOOKUP(E25,Sheet2!$AG$1:$AH$975,2,FALSE),0) -> 0 | Z25: =IFERROR(VLOOKUP(F25,Sheet2!$AA$1:$AB$975,2,FALSE),0) -> 1 | AA25: =IFERROR(VLOOKUP(F25,Sheet2!$AC$1:$AD$975,2,FALSE),0) -> 18 | AB25: =IFERROR(VLOOKUP(F25,Sheet2!$AE$2:$AF$6539,2,FALSE),0) -> 28 | AC25: =IFERROR(VLOOKUP(F25,Sheet2!$AG$2:$AH$6539,2,FALSE),0) -> 0.5484 | AE25: 62 | AF25: 8 | AG25: 0 | AH25: 0 | AI25: 8 | AJ25: =SUM(AE25+AI25) -> 70 | AK25: =SUM(AJ25*O25) -> 544.32 | AL25: 0 | AM25: 0
A26: GoBros | B26: 46173 | D26: 048323013826 | E26: WIGF1061_051_wht_3 | F26: ZZWIGF1061_051_wht_3 | G26: #N/A | H26: FBM Only | I26: F1061 | J26: Wigwam Master Lightweight Crew Socks | K26: White | L26: 13 | O26: 7.776 | R26: =IFERROR(VLOOKUP(E26,Sheet6!$A$2:$B$500,2,FALSE),0) -> 0 | S26: =IFERROR(VLOOKUP(E26,Sheet6!$C$2:$D$35017,2,FALSE),0) -> 0 | U26: =IFERROR(VLOOKUP(E26,Sheet2!$AA$1:$AB$975,2,FALSE),0) -> 8 | V26: =IFERROR(VLOOKUP(E26,Sheet2!$AC$1:$AD$975,2,FALSE),0) -> 144 | W26: =IFERROR(VLOOKUP(E26,Sheet2!$AE$1:$AF$975,2,FALSE),0) -> 20 | X26: =IFERROR(VLOOKUP(E26,Sheet2!$AG$1:$AH$975,2,FALSE),0) -> 0.9688 | Z26: =IFERROR(VLOOKUP(F26,Sheet2!$AA$1:$AB$975,2,FALSE),0) -> 0 | AA26: =IFERROR(VLOOKUP(F26,Sheet2!$AC$1:$AD$975,2,FALSE),0) -> 0 | AB26: =IFERROR(VLOOKUP(F26,Sheet2!$AE$2:$AF$6539,2,FALSE),0) -> 0 | AC26: =IFERROR(VLOOKUP(F26,Sheet2!$AG$2:$AH$6539,2,FALSE),0) -> 0 | AE26: 46 | AF26: 0 | AG26: 0 | AH26: 0 | AI26: 0 | AJ26: =SUM(AE26+AI26) -> 46 | AK26: =SUM(AJ26*O26) -> 357.696 | AL26: 0 | AM26: 0
A27: GoBros | B27: 46173 | D27: 048323013833 | E27: WIGF1061_051_wht_4 | F27: ZZWIGF1061_051_wht_4 | G27: #N/A | H27: FBM Only | I27: F1061 | J27: Wigwam Master Lightweight Crew Socks | K27: White | L27: 14 | O27: 7.776 | R27: =IFERROR(VLOOKUP(E27,Sheet6!$A$2:$B$500,2,FALSE),0) -> 0 | S27: =IFERROR(VLOOKUP(E27,Sheet6!$C$2:$D$35017,2,FALSE),0) -> 0 | U27: =IFERROR(VLOOKUP(E27,Sheet2!$AA$1:$AB$975,2,FALSE),0) -> 0 | V27: =IFERROR(VLOOKUP(E27,Sheet2!$AC$1:$AD$975,2,FALSE),0) -> 0 | W27: =IFERROR(VLOOKUP(E27,Sheet2!$AE$1:$AF$975,2,FALSE),0) -> 0 | X27: =IFERROR(VLOOKUP(E27,Sheet2!$AG$1:$AH$975,2,FALSE),0) -> 0 | Z27: =IFERROR(VLOOKUP(F27,Sheet2!$AA$1:$AB$975,2,FALSE),0) -> 0 | AA27: =IFERROR(VLOOKUP(F27,Sheet2!$AC$1:$AD$975,2,FALSE),0) -> 0 | AB27: =IFERROR(VLOOKUP(F27,Sheet2!$AE$2:$AF$6539,2,FALSE),0) -> 0 | AC27: =IFERROR(VLOOKUP(F27,Sheet2!$AG$2:$AH$6539,2,FALSE),0) -> 0 | AE27: 27 | AF27: 16 | AG27: 0 | AH27: 0 | AI27: 16 | AJ27: =SUM(AE27+AI27) -> 43 | AK27: =SUM(AJ27*O27) -> 334.368 | AL27: 0 | AM27: 0
A28: GoBros | B28: 46173 | D28: 048323573894 | E28: WIGF1061_052_blk_0 | F28: ZZWIGF1061_052_blk_0 | G28: #N/A | H28: FBM Only | I28: F1061 | J28: Wigwam Master Lightweight Crew Socks | K28: Black | L28: 10 | O28: 7.776 | R28: =IFERROR(VLOOKUP(E28,Sheet6!$A$2:$B$500,2,FALSE),0) -> 0 | S28: =IFERROR(VLOOKUP(E28,Sheet6!$C$2:$D$35017,2,FALSE),0) -> 0 | U28: =IFERROR(VLOOKUP(E28,Sheet2!$AA$1:$AB$975,2,FALSE),0) -> 0 | V28: =IFERROR(VLOOKUP(E28,Sheet2!$AC$1:$AD$975,2,FALSE),0) -> 0 | W28: =IFERROR(VLOOKUP(E28,Sheet2!$AE$1:$AF$975,2,FALSE),0) -> 0 | X28: =IFERROR(VLOOKUP(E28,Sheet2!$AG$1:$AH$975,2,FALSE),0) -> 0 | Z28: =IFERROR(VLOOKUP(F28,Sheet2!$AA$1:$AB$975,2,FALSE),0) -> 0 | AA28: =IFERROR(VLOOKUP(F28,Sheet2!$AC$1:$AD$975,2,FALSE),0) -> 0 | AB28: =IFERROR(VLOOKUP(F28,Sheet2!$AE$2:$AF$6539,2,FALSE),0) -> 0 | AC28: =IFERROR(VLOOKUP(F28,Sheet2!$AG$2:$AH$6539,2,FALSE),0) -> 0 | AE28: 12 | AF28: 6 | AG28: 0 | AH28: 0 | AI28: 6 | AJ28: =SUM(AE28+AI28) -> 18 | AK28: =SUM(AJ28*O28) -> 139.968 | AL28: 0 | AM28: 0
A29: GoBros | B29: 46173 | D29: 048323573900 | E29: WIGF1061_052_blk_1 | F29: ZZWIGF1061_052_blk_1 | G29: #N/A | H29: FBM Only | I29: F1061 | J29: Wigwam Master Lightweight Crew Socks | K29: Black | L29: 11 | O29: 7.776 | R29: =IFERROR(VLOOKUP(E29,Sheet6!$A$2:$B$500,2,FALSE),0) -> 0 | S29: =IFERROR(VLOOKUP(E29,Sheet6!$C$2:$D$35017,2,FALSE),0) -> 0 | U29: =IFERROR(VLOOKUP(E29,Sheet2!$AA$1:$AB$975,2,FALSE),0) -> 0 | V29: =IFERROR(VLOOKUP(E29,Sheet2!$AC$1:$AD$975,2,FALSE),0) -> 0 | W29: =IFERROR(VLOOKUP(E29,Sheet2!$AE$1:$AF$975,2,FALSE),0) -> 0 | X29: =IFERROR(VLOOKUP(E29,Sheet2!$AG$1:$AH$975,2,FALSE),0) -> 0 | Z29: =IFERROR(VLOOKUP(F29,Sheet2!$AA$1:$AB$975,2,FALSE),0) -> 0 | AA29: =IFERROR(VLOOKUP(F29,Sheet2!$AC$1:$AD$975,2,FALSE),0) -> 0 | AB29: =IFERROR(VLOOKUP(F29,Sheet2!$AE$2:$AF$6539,2,FALSE),0) -> 0 | AC29: =IFERROR(VLOOKUP(F29,Sheet2!$AG$2:$AH$6539,2,FALSE),0) -> 0 | AE29: 26 | AF29: 6 | AG29: 0 | AH29: 0 | AI29: 6 | AJ29: =SUM(AE29+AI29) -> 32 | AK29: =SUM(AJ29*O29) -> 248.832 | AL29: 0 | AM29: 0
A30: GoBros | B30: 46173 | D30: 048323573917 | E30: WIGF1061_052_blk_2 | F30: ZZWIGF1061_052_blk_2 | G30: #N/A | H30: FBM Only | I30: F1061 | J30: Wigwam Master Lightweight Crew Socks | K30: Black | L30: 12 | O30: 7.776 | R30: =IFERROR(VLOOKUP(E30,Sheet6!$A$2:$B$500,2,FALSE),0) -> 0 | S30: =IFERROR(VLOOKUP(E30,Sheet6!$C$2:$D$35017,2,FALSE),0) -> 0 | U30: =IFERROR(VLOOKUP(E30,Sheet2!$AA$1:$AB$975,2,FALSE),0) -> 0 | V30: =IFERROR(VLOOKUP(E30,Sheet2!$AC$1:$AD$975,2,FALSE),0) -> 0 | W30: =IFERROR(VLOOKUP(E30,Sheet2!$AE$1:$AF$975,2,FALSE),0) -> 0 | X30: =IFERROR(VLOOKUP(E30,Sheet2!$AG$1:$AH$975,2,FALSE),0) -> 0 | Z30: =IFERROR(VLOOKUP(F30,Sheet2!$AA$1:$AB$975,2,FALSE),0) -> 0 | AA30: =IFERROR(VLOOKUP(F30,Sheet2!$AC$1:$AD$975,2,FALSE),0) -> 0 | AB30: =IFERROR(VLOOKUP(F30,Sheet2!$AE$2:$AF$6539,2,FALSE),0) -> 0 | AC30: =IFERROR(VLOOKUP(F30,Sheet2!$AG$2:$AH$6539,2,FALSE),0) -> 0 | AE30: 19 | AF30: 18 | AG30: 0 | AH30: 0 | AI30: 18 | AJ30: =SUM(AE30+AI30) -> 37 | AK30: =SUM(AJ30*O30) -> 287.712 | AL30: 0 | AM30: 0
A31: GoBros | B31: 46173 | D31: 048323573924 | E31: WIGF1061_052_blk_3 | F31: ZZWIGF1061_052_blk_3 | G31: #N/A | H31: FBM Only | I31: F1061 | J31: Wigwam Master Lightweight Crew Socks | K31: Black | L31: 13 | O31: 7.776 | R31: =IFERROR(VLOOKUP(E31,Sheet6!$A$2:$B$500,2,FALSE),0) -> 0 | S31: =IFERROR(VLOOKUP(E31,Sheet6!$C$2:$D$35017,2,FALSE),0) -> 0 | U31: =IFERROR(VLOOKUP(E31,Sheet2!$AA$1:$AB$975,2,FALSE),0) -> 0 | V31: =IFERROR(VLOOKUP(E31,Sheet2!$AC$1:$AD$975,2,FALSE),0) -> 0 | W31: =IFERROR(VLOOKUP(E31,Sheet2!$AE$1:$AF$975,2,FALSE),0) -> 0 | X31: =IFERROR(VLOOKUP(E31,Sheet2!$AG$1:$AH$975,2,FALSE),0) -> 0 | Z31: =IFERROR(VLOOKUP(F31,Sheet2!$AA$1:$AB$975,2,FALSE),0) -> 0 | AA31: =IFERROR(VLOOKUP(F31,Sheet2!$AC$1:$AD$975,2,FALSE),0) -> 0 | AB31: =IFERROR(VLOOKUP(F31,Sheet2!$AE$2:$AF$6539,2,FALSE),0) -> 0 | AC31: =IFERROR(VLOOKUP(F31,Sheet2!$AG$2:$AH$6539,2,FALSE),0) -> 0 | AE31: 63 | AF31: 2 | AG31: 0 | AH31: 0 | AI31: 2 | AJ31: =SUM(AE31+AI31) -> 65 | AK31: =SUM(AJ31*O31) -> 505.44 | AL31: 0 | AM31: 0
A32: GoBros | B32: 46173 | D32: 048323014090 | E32: WIGF1071_051_wht_0 | F32: ZZWIGF1071_051_wht_0 | G32: #N/A | H32: FBA | I32: F1071 | J32: Wigwam 622 Socks | K32: White | L32: Med | O32: 8.64 | R32: =IFERROR(VLOOKUP(E32,Sheet6!$A$2:$B$500,2,FALSE),0) -> 0 | S32: =IFERROR(VLOOKUP(E32,Sheet6!$C$2:$D$35017,2,FALSE),0) -> 0 | U32: =IFERROR(VLOOKUP(E32,Sheet2!$AA$1:$AB$975,2,FALSE),0) -> 0 | V32: =IFERROR(VLOOKUP(E32,Sheet2!$AC$1:$AD$975,2,FALSE),0) -> 0 | W32: =IFERROR(VLOOKUP(E32,Sheet2!$AE$1:$AF$975,2,FALSE),0) -> 0 | X32: =IFERROR(VLOOKUP(E32,Sheet2!$AG$1:$AH$975,2,FALSE),0) -> 0 | Z32: =IFERROR(VLOOKUP(F32,Sheet2!$AA$1:$AB$975,2,FALSE),0) -> 11 | AA32: =IFERROR(VLOOKUP(F32,Sheet2!$AC$1:$AD$975,2,FALSE),0) -> 219.89 | AB32: =IFERROR(VLOOKUP(F32,Sheet2!$AE$2:$AF$6539,2,FALSE),0) -> 69 | AC32: =IFERROR(VLOOKUP(F32,Sheet2!$AG$2:$AH$6539,2,FALSE),0) -> 1 | AE32: 0 | AF32: 13 | AG32: 0 | AH32: 0 | AI32: 13 | AJ32: =SUM(AE32+AI32) -> 13 | AK32: =SUM(AJ32*O32) -> 112.32 | AL32: 12 | AM32: 12
A33: GoBros | B33: 46173 | D33: 048323014083 | E33: WIGF1071_051_wht_1 | F33: ZZWIGF1071_051_wht_1 | G33: #N/A | H33: FBA | I33: F1071 | J33: Wigwam 622 Socks | K33: White | L33: Large | O33: 8.64 | R33: =IFERROR(VLOOKUP(E33,Sheet6!$A$2:$B$500,2,FALSE),0) -> 0 | S33: =IFERROR(VLOOKUP(E33,Sheet6!$C$2:$D$35017,2,FALSE),0) -> 0 | U33: =IFERROR(VLOOKUP(E33,Sheet2!$AA$1:$AB$975,2,FALSE),0) -> 0 | V33: =IFERROR(VLOOKUP(E33,Sheet2!$AC$1:$AD$975,2,FALSE),0) -> 0 | W33: =IFERROR(VLOOKUP(E33,Sheet2!$AE$1:$AF$975,2,FALSE),0) -> 0 | X33: =IFERROR(VLOOKUP(E33,Sheet2!$AG$1:$AH$975,2,FALSE),0) -> 0 | Z33: =IFERROR(VLOOKUP(F33,Sheet2!$AA$1:$AB$975,2,FALSE),0) -> 12 | AA33: =IFERROR(VLOOKUP(F33,Sheet2!$AC$1:$AD$975,2,FALSE),0) -> 239.88 | AB33: =IFERROR(VLOOKUP(F33,Sheet2!$AE$2:$AF$6539,2,FALSE),0) -> 103 | AC33: =IFERROR(VLOOKUP(F33,Sheet2!$AG$2:$AH$6539,2,FALSE),0) -> 0.7823 | AE33: 24 | AF33: 1 | AG33: 6 | AH33: 1 | AI33: 8 | AJ33: =SUM(AE33+AI33) -> 32 | AK33: =SUM(AJ33*O33) -> 276.48 | AL33: 12 | AM33: 30
A34: GoBros | B34: 46173 | D34: 048323014106 | E34: WIGF1071_051_wht_2 | F34: ZZWIGF1071_051_wht_2 | G34: #N/A | H34: FBA | I34: F1071 | J34: Wigwam 622 Socks | K34: White | L34: X-Large | O34: 8.64 | R34: =IFERROR(VLOOKUP(E34,Sheet6!$A$2:$B$500,2,FALSE),0) -> 0 | S34: =IFERROR(VLOOKUP(E34,Sheet6!$C$2:$D$35017,2,FALSE),0) -> 0 | U34: =IFERROR(VLOOKUP(E34,Sheet2!$AA$1:$AB$975,2,FALSE),0) -> 0 | V34: =IFERROR(VLOOKUP(E34,Sheet2!$AC$1:$AD$975,2,FALSE),0) -> 0 | W34: =IFERROR(VLOOKUP(E34,Sheet2!$AE$1:$AF$975,2,FALSE),0) -> 0 | X34: =IFERROR(VLOOKUP(E34,Sheet2!$AG$1:$AH$975,2,FALSE),0) -> 0 | Z34: =IFERROR(VLOOKUP(F34,Sheet2!$AA$1:$AB$975,2,FALSE),0) -> 4 | AA34: =IFERROR(VLOOKUP(F34,Sheet2!$AC$1:$AD$975,2,FALSE),0) -> 79.96 | AB34: =IFERROR(VLOOKUP(F34,Sheet2!$AE$2:$AF$6539,2,FALSE),0) -> 42 | AC34: =IFERROR(VLOOKUP(F34,Sheet2!$AG$2:$AH$6539,2,FALSE),0) -> 0.2157 | AE34: 3 | AF34: 2 | AG34: 0 | AH34: 0 | AI34: 2 | AJ34: =SUM(AE34+AI34) -> 5 | AK34: =SUM(AJ34*O34) -> 43.2 | AL34: 6 | AM34: 0
A35: GoBros | B35: 46173 | D35: 048323014120 | E35: WIGF1071_052_blk_0 | F35: ZZWIGF1071_052_blk_0 | G35: #N/A | H35: FBM Only | I35: F1071 | J35: Wigwam 622 Socks | K35: Black | L35: Medium | O35: 8.64 | R35: =IFERROR(VLOOKUP(E35,Sheet6!$A$2:$B$500,2,FALSE),0) -> 0 | S35: =IFERROR(VLOOKUP(E35,Sheet6!$C$2:$D$35017,2,FALSE),0) -> 0 | U35: =IFERROR(VLOOKUP(E35,Sheet2!$AA$1:$AB$975,2,FALSE),0) -> 0 | V35: =IFERROR(VLOOKUP(E35,Sheet2!$AC$1:$AD$975,2,FALSE),0) -> 0 | W35: =IFERROR(VLOOKUP(E35,Sheet2!$AE$1:$AF$975,2,FALSE),0) -> 0 | X35: =IFERROR(VLOOKUP(E35,Sheet2!$AG$1:$AH$975,2,FALSE),0) -> 0 | Z35: =IFERROR(VLOOKUP(F35,Sheet2!$AA$1:$AB$975,2,FALSE),0) -> 1 | AA35: =IFERROR(VLOOKUP(F35,Sheet2!$AC$1:$AD$975,2,FALSE),0) -> 19.99 | AB35: =IFERROR(VLOOKUP(F35,Sheet2!$AE$2:$AF$6539,2,FALSE),0) -> 26 | AC35: =IFERROR(VLOOKUP(F35,Sheet2!$AG$2:$AH$6539,2,FALSE),0) -> 0.4286 | AE35: 15 | AF35: 23 | AG35: 0 | AH35: 1 | AI35: 24 | AJ35: =SUM(AE35+AI35) -> 39 | AK35: =SUM(AJ35*O35) -> 336.96 | AL35: 0 | AM35: 0
A36: GoBros | B36: 46173 | D36: 048323014113 | E36: WIGF1071_052_blk_1 | F36: ZZWIGF1071_052_blk_1 | G36: B000G7W9CO | H36: FBM Only | I36: F1071 | J36: Wigwam 622 Socks | K36: Black | L36: Large | O36: 8.64 | R36: =IFERROR(VLOOKUP(E36,Sheet6!$A$2:$B$500,2,FALSE),0) -> 0 | S36: =IFERROR(VLOOKUP(E36,Sheet6!$C$2:$D$35017,2,FALSE),0) -> 0 | U36: =IFERROR(VLOOKUP(E36,Sheet2!$AA$1:$AB$975,2,FALSE),0) -> 0 | V36: =IFERROR(VLOOKUP(E36,Sheet2!$AC$1:$AD$975,2,FALSE),0) -> 0 | W36: =IFERROR(VLOOKUP(E36,Sheet2!$AE$1:$AF$975,2,FALSE),0) -> 0 | X36: =IFERROR(VLOOKUP(E36,Sheet2!$AG$1:$AH$975,2,FALSE),0) -> 0 | Z36: =IFERROR(VLOOKUP(F36,Sheet2!$AA$1:$AB$975,2,FALSE),0) -> 1 | AA36: =IFERROR(VLOOKUP(F36,Sheet2!$AC$1:$AD$975,2,FALSE),0) -> 19.99 | AB36: =IFERROR(VLOOKUP(F36,Sheet2!$AE$2:$AF$6539,2,FALSE),0) -> 25 | AC36: =IFERROR(VLOOKUP(F36,Sheet2!$AG$2:$AH$6539,2,FALSE),0) -> 0.3 | AE36: 27 | AF36: 1 | AG36: 0 | AH36: 0 | AI36: 1 | AJ36: =SUM(AE36+AI36) -> 28 | AK36: =SUM(AJ36*O36) -> 241.92 | AL36: 12 | AM36: 12
A37: GoBros | B37: 46173 | D37: 048323014328 | E37: WIGF1072_051_wht_0 | F37: ZZWIGF1072_051_wht_0 | G37: #N/A | H37: FBM Only | I37: F1072 | J37: Wigwam Advantage Crew Socks | K37: White | L37: Medium | O37: 6.048 | R37: =IFERROR(VLOOKUP(E37,Sheet6!$A$2:$B$500,2,FALSE),0) -> 0 | S37: =IFERROR(VLOOKUP(E37,Sheet6!$C$2:$D$35017,2,FALSE),0) -> 0 | U37: =IFERROR(VLOOKUP(E37,Sheet2!$AA$1:$AB$975,2,FALSE),0) -> 0 | V37: =IFERROR(VLOOKUP(E37,Sheet2!$AC$1:$AD$975,2,FALSE),0) -> 0 | W37: =IFERROR(VLOOKUP(E37,Sheet2!$AE$1:$AF$975,2,FALSE),0) -> 0 | X37: =IFERROR(VLOOKUP(E37,Sheet2!$AG$1:$AH$975,2,FALSE),0) -> 0 | Z37: =IFERROR(VLOOKUP(F37,Sheet2!$AA$1:$AB$975,2,FALSE),0) -> 0 | AA37: =IFERROR(VLOOKUP(F37,Sheet2!$AC$1:$AD$975,2,FALSE),0) -> 0 | AB37: =IFERROR(VLOOKUP(F37,Sheet2!$AE$2:$AF$6539,2,FALSE),0) -> 0 | AC37: =IFERROR(VLOOKUP(F37,Sheet2!$AG$2:$AH$6539,2,FALSE),0) -> 0 | AE37: 67 | AF37: 0 | AG37: 0 | AH37: 0 | AI37: 0 | AJ37: =SUM(AE37+AI37) -> 67 | AK37: =SUM(AJ37*O37) -> 405.216 | AL37: 0 | AM37: 0
A38: GoBros | B38: 46173 | D38: 048323014311 | E38: WIGF1072_051_wht_1 | F38: ZZWIGF1072_051_wht_1 | G38: #N/A | H38: FBA | I38: F1072 | J38: Wigwam Advantage Crew Socks | K38: White | L38: Large | O38: 6.048 | R38: =IFERROR(VLOOKUP(E38,Sheet6!$A$2:$B$500,2,FALSE),0) -> 5 | S38: =IFERROR(VLOOKUP(E38,Sheet6!$C$2:$D$35017,2,FALSE),0) -> 65.8 | U38: =IFERROR(VLOOKUP(E38,Sheet2!$AA$1:$AB$975,2,FALSE),0) -> 0 | V38: =IFERROR(VLOOKUP(E38,Sheet2!$AC$1:$AD$975,2,FALSE),0) -> 0 | W38: =IFERROR(VLOOKUP(E38,Sheet2!$AE$1:$AF$975,2,FALSE),0) -> 0 | X38: =IFERROR(VLOOKUP(E38,Sheet2!$AG$1:$AH$975,2,FALSE),0) -> 0 | Z38: =IFERROR(VLOOKUP(F38,Sheet2!$AA$1:$AB$975,2,FALSE),0) -> 0 | AA38: =IFERROR(VLOOKUP(F38,Sheet2!$AC$1:$AD$975,2,FALSE),0) -> 0 | AB38: =IFERROR(VLOOKUP(F38,Sheet2!$AE$2:$AF$6539,2,FALSE),0) -> 0 | AC38: =IFERROR(VLOOKUP(F38,Sheet2!$AG$2:$AH$6539,2,FALSE),0) -> 0 | AE38: 69 | AF38: 0 | AG38: 0 | AH38: 0 | AI38: 0 | AJ38: =SUM(AE38+AI38) -> 69 | AK38: =SUM(AJ38*O38) -> 417.312 | AL38: 0 | AM38: 0
A39: GoBros | B39: 46173 | D39: 048323014335 | E39: WIGF1072_051_wht_2 | F39: ZZWIGF1072_051_wht_2 | G39: #N/A | H39: FBA | I39: F1072 | J39: Wigwam Advantage Crew Socks | K39: White | L39: X-Large | O39: 6.048 | R39: =IFERROR(VLOOKUP(E39,Sheet6!$A$2:$B$500,2,FALSE),0) -> 0 | S39: =IFERROR(VLOOKUP(E39,Sheet6!$C$2:$D$35017,2,FALSE),0) -> 0 | U39: =IFERROR(VLOOKUP(E39,Sheet2!$AA$1:$AB$975,2,FALSE),0) -> 2 | V39: =IFERROR(VLOOKUP(E39,Sheet2!$AC$1:$AD$975,2,FALSE),0) -> 28 | W39: =IFERROR(VLOOKUP(E39,Sheet2!$AE$1:$AF$975,2,FALSE),0) -> 84 | X39: =IFERROR(VLOOKUP(E39,Sheet2!$AG$1:$AH$975,2,FALSE),0) -> 0.9902 | Z39: =IFERROR(VLOOKUP(F39,Sheet2!$AA$1:$AB$975,2,FALSE),0) -> 0 | AA39: =IFERROR(VLOOKUP(F39,Sheet2!$AC$1:$AD$975,2,FALSE),0) -> 0 | AB39: =IFERROR(VLOOKUP(F39,Sheet2!$AE$2:$AF$6539,2,FALSE),0) -> 0 | AC39: =IFERROR(VLOOKUP(F39,Sheet2!$AG$2:$AH$6539,2,FALSE),0) -> 0 | AE39: 11 | AF39: 0 | AG39: 0 | AH39: 0 | AI39: 0 | AJ39: =SUM(AE39+AI39) -> 11 | AK39: =SUM(AJ39*O39) -> 66.528 | AL39: 0 | AM39: 0
A40: GoBros | B40: 46173 | D40: 048323015820 | E40: WIGF1086_051_nat_0 | F40: ZZWIGF1086_051_nat_0 | G40: #N/A | H40: FBA | I40: F1086 | J40: Wigwam 625 Wool Crew Socks | K40: Natural White | L40: Medium | O40: 9.9 | R40: =IFERROR(VLOOKUP(E40,Sheet6!$A$2:$B$500,2,FALSE),0) -> 2 | S40: =IFERROR(VLOOKUP(E40,Sheet6!$C$2:$D$35017,2,FALSE),0) -> 44 | U40: =IFERROR(VLOOKUP(E40,Sheet2!$AA$1:$AB$975,2,FALSE),0) -> 0 | V40: =IFERROR(VLOOKUP(E40,Sheet2!$AC$1:$AD$975,2,FALSE),0) -> 0 | W40: =IFERROR(VLOOKUP(E40,Sheet2!$AE$1:$AF$975,2,FALSE),0) -> 0 | X40: =IFERROR(VLOOKUP(E40,Sheet2!$AG$1:$AH$975,2,FALSE),0) -> 0 | Z40: =IFERROR(VLOOKUP(F40,Sheet2!$AA$1:$AB$975,2,FALSE),0) -> 32 | AA40: =IFERROR(VLOOKUP(F40,Sheet2!$AC$1:$AD$975,2,FALSE),0) -> 703.68 | AB40: =IFERROR(VLOOKUP(F40,Sheet2!$AE$2:$AF$6539,2,FALSE),0) -> 88 | AC40: =IFERROR(VLOOKUP(F40,Sheet2!$AG$2:$AH$6539,2,FALSE),0) -> 0.9116 | AE40: 34 | AF40: 64 | AG40: 0 | AH40: 1 | AI40: 65 | AJ40: =SUM(AE40+AI40) -> 99 | AK40: =SUM(AJ40*O40) -> 980.1 | AL40: 30 | AM40: 0
A41: GoBros | B41: 46173 | D41: 048323015813 | E41: WIGF1086_051_nat_1 | F41: ZZWIGF1086_051_nat_1 | G41: #N/A | H41: FBM Only | I41: F1086 | J41: Wigwam 625 Wool Crew Socks | K41: Natural White | L41: Large | O41: 9.9 | R41: =IFERROR(VLOOKUP(E41,Sheet6!$A$2:$B$500,2,FALSE),0) -> 0 | S41: =IFERROR(VLOOKUP(E41,Sheet6!$C$2:$D$35017,2,FALSE),0) -> 0 | U41: =IFERROR(VLOOKUP(E41,Sheet2!$AA$1:$AB$975,2,FALSE),0) -> 0 | V41: =IFERROR(VLOOKUP(E41,Sheet2!$AC$1:$AD$975,2,FALSE),0) -> 0 | W41: =IFERROR(VLOOKUP(E41,Sheet2!$AE$1:$AF$975,2,FALSE),0) -> 0 | X41: =IFERROR(VLOOKUP(E41,Sheet2!$AG$1:$AH$975,2,FALSE),0) -> 0 | Z41: =IFERROR(VLOOKUP(F41,Sheet2!$AA$1:$AB$975,2,FALSE),0) -> 5 | AA41: =IFERROR(VLOOKUP(F41,Sheet2!$AC$1:$AD$975,2,FALSE),0) -> 109.95 | AB41: =IFERROR(VLOOKUP(F41,Sheet2!$AE$2:$AF$6539,2,FALSE),0) -> 106 | AC41: =IFERROR(VLOOKUP(F41,Sheet2!$AG$2:$AH$6539,2,FALSE),0) -> 0.1989 | AE41: 0 | AF41: 0 | AG41: 2 | AH41: 0 | AI41: 2 | AJ41: =SUM(AE41+AI41) -> 2 | AK41: =SUM(AJ41*O41) -> 19.8 | AL41: 0 | AM41: 270
A42: GoBros | B42: 46173 | D42: 048323015837 | E42: WIGF1086_051_nat_2 | F42: ZZWIGF1086_051_nat_2 | G42: #N/A | H42: FBM Only | I42: F1086 | J42: Wigwam 625 Wool Crew Socks | K42: Natural White | L42: X-Large | O42: 9.9 | R42: =IFERROR(VLOOKUP(E42,Sheet6!$A$2:$B$500,2,FALSE),0) -> 1 | S42: =IFERROR(VLOOKUP(E42,Sheet6!$C$2:$D$35017,2,FALSE),0) -> 22 | U42: =IFERROR(VLOOKUP(E42,Sheet2!$AA$1:$AB$975,2,FALSE),0) -> 4 | V42: =IFERROR(VLOOKUP(E42,Sheet2!$AC$1:$AD$975,2,FALSE),0) -> 87.96 | W42: =IFERROR(VLOOKUP(E42,Sheet2!$AE$1:$AF$975,2,FALSE),0) -> 191 | X42: =IFERROR(VLOOKUP(E42,Sheet2!$AG$1:$AH$975,2,FALSE),0) -> 0.3222 | Z42: =IFERROR(VLOOKUP(F42,Sheet2!$AA$1:$AB$975,2,FALSE),0) -> 2 | AA42: =IFERROR(VLOOKUP(F42,Sheet2!$AC$1:$AD$975,2,FALSE),0) -> 43.98 | AB42: =IFERROR(VLOOKUP(F42,Sheet2!$AE$2:$AF$6539,2,FALSE),0) -> 191 | AC42: =IFERROR(VLOOKUP(F42,Sheet2!$AG$2:$AH$6539,2,FALSE),0) -> 0.3222 | AE42: 58 | AF42: 0 | AG42: 6 | AH42: 0 | AI42: 6 | AJ42: =SUM(AE42+AI42) -> 64 | AK42: =SUM(AJ42*O42) -> 633.6 | AL42: 54 | AM42: 0
A43: GoBros | B43: 46173 | D43: 048323666077 | E43: WIGF1091_052_blk_2 | F43: ZZWIGF1091_052_blk_2 | G43: #N/A | H43: FBM Only | I43: F1091 | J43: Wigwam The Icon Lightweight Crew Socks | K43: Black | L43: Large | O43: 8.64 | R43: =IFERROR(VLOOKUP(E43,Sheet6!$A$2:$B$500,2,FALSE),0) -> 0 | S43: =IFERROR(VLOOKUP(E43,Sheet6!$C$2:$D$35017,2,FALSE),0) -> 0 | U43: =IFERROR(VLOOKUP(E43,Sheet2!$AA$1:$AB$975,2,FALSE),0) -> 0 | V43: =IFERROR(VLOOKUP(E43,Sheet2!$AC$1:$AD$975,2,FALSE),0) -> 0 | W43: =IFERROR(VLOOKUP(E43,Sheet2!$AE$1:$AF$975,2,FALSE),0) -> 0 | X43: =IFERROR(VLOOKUP(E43,Sheet2!$AG$1:$AH$975,2,FALSE),0) -> 0 | Z43: =IFERROR(VLOOKUP(F43,Sheet2!$AA$1:$AB$975,2,FALSE),0) -> 5 | AA43: =IFERROR(VLOOKUP(F43,Sheet2!$AC$1:$AD$975,2,FALSE),0) -> 100 | AB43: =IFERROR(VLOOKUP(F43,Sheet2!$AE$2:$AF$6539,2,FALSE),0) -> 24 | AC43: =IFERROR(VLOOKUP(F43,Sheet2!$AG$2:$AH$6539,2,FALSE),0) -> 1 | AE43: 15 | AF43: 6 | AG43: 0 | AH43: 0 | AI43: 6 | AJ43: =SUM(AE43+AI43) -> 21 | AK43: =SUM(AJ43*O43) -> 181.44 | AL43: 6 | AM43: 12
A44: GoBros | B44: 46173 | D44: 048323666084 | E44: WIGF1091_115_nat_1 | F44: ZZWIGF1091_115_nat_1 | G44: #N/A | H44: FBM Only | I44: F1091 | J44: Wigwam The Icon Lightweight Crew Socks | K44: White | L44: Medium | O44: 8.64 | R44: =IFERROR(VLOOKUP(E44,Sheet6!$A$2:$B$500,2,FALSE),0) -> 0 | S44: =IFERROR(VLOOKUP(E44,Sheet6!$C$2:$D$35017,2,FALSE),0) -> 0 | U44: =IFERROR(VLOOKUP(E44,Sheet2!$AA$1:$AB$975,2,FALSE),0) -> 0 | V44: =IFERROR(VLOOKUP(E44,Sheet2!$AC$1:$AD$975,2,FALSE),0) -> 0 | W44: =IFERROR(VLOOKUP(E44,Sheet2!$AE$1:$AF$975,2,FALSE),0) -> 0 | X44: =IFERROR(VLOOKUP(E44,Sheet2!$AG$1:$AH$975,2,FALSE),0) -> 0 | Z44: =IFERROR(VLOOKUP(F44,Sheet2!$AA$1:$AB$975,2,FALSE),0) -> 0 | AA44: =IFERROR(VLOOKUP(F44,Sheet2!$AC$1:$AD$975,2,FALSE),0) -> 0 | AB44: =IFERROR(VLOOKUP(F44,Sheet2!$AE$2:$AF$6539,2,FALSE),0) -> 0 | AC44: =IFERROR(VLOOKUP(F44,Sheet2!$AG$2:$AH$6539,2,FALSE),0) -> 0 | AE44: 0 | AF44: 0 | AG44: 0 | AH44: 0 | AI44: 0 | AJ44: =SUM(AE44+AI44) -> 0 | AK44: =SUM(AJ44*O44) -> 0 | AL44: 0 | AM44: 0
A45: GoBros | B45: 46173 | D45: 048323666091 | E45: WIGF1091_115_nat_2 | F45: ZZWIGF1091_115_nat_2 | G45: #N/A | H45: FBM Only | I45: F1091 | J45: Wigwam The Icon Lightweight Crew Socks | K45: White | L45: Large | O45: 8.64 | R45: =IFERROR(VLOOKUP(E45,Sheet6!$A$2:$B$500,2,FALSE),0) -> 0 | S45: =IFERROR(VLOOKUP(E45,Sheet6!$C$2:$D$35017,2,FALSE),0) -> 0 | U45: =IFERROR(VLOOKUP(E45,Sheet2!$AA$1:$AB$975,2,FALSE),0) -> 0 | V45: =IFERROR(VLOOKUP(E45,Sheet2!$AC$1:$AD$975,2,FALSE),0) -> 0 | W45: =IFERROR(VLOOKUP(E45,Sheet2!$AE$1:$AF$975,2,FALSE),0) -> 0 | X45: =IFERROR(VLOOKUP(E45,Sheet2!$AG$1:$AH$975,2,FALSE),0) -> 0 | Z45: =IFERROR(VLOOKUP(F45,Sheet2!$AA$1:$AB$975,2,FALSE),0) -> 0 | AA45: =IFERROR(VLOOKUP(F45,Sheet2!$AC$1:$AD$975,2,FALSE),0) -> 0 | AB45: =IFERROR(VLOOKUP(F45,Sheet2!$AE$2:$AF$6539,2,FALSE),0) -> 0 | AC45: =IFERROR(VLOOKUP(F45,Sheet2!$AG$2:$AH$6539,2,FALSE),0) -> 0 | AE45: 6 | AF45: 9 | AG45: 0 | AH45: 0 | AI45: 9 | AJ45: =SUM(AE45+AI45) -> 15 | AK45: =SUM(AJ45*O45) -> 129.6 | AL45: 0 | AM45: 0
A46: GoBros | B46: 46173 | D46: 048323187701 | E46: WIGF1140_052_bla_1 | F46: ZZWIGF1140_052_bla_1 | G46: #N/A | H46: FBM Only | I46: F1140 | J46: Wigwam At Work Steel Toe Heavyweight Socks | K46: Black | L46: Medium | O46: 6.912 | R46: =IFERROR(VLOOKUP(E46,Sheet6!$A$2:$B$500,2,FALSE),0) -> 0 | S46: =IFERROR(VLOOKUP(E46,Sheet6!$C$2:$D$35017,2,FALSE),0) -> 0 | U46: =IFERROR(VLOOKUP(E46,Sheet2!$AA$1:$AB$975,2,FALSE),0) -> 0 | V46: =IFERROR(VLOOKUP(E46,Sheet2!$AC$1:$AD$975,2,FALSE),0) -> 0 | W46: =IFERROR(VLOOKUP(E46,Sheet2!$AE$1:$AF$975,2,FALSE),0) -> 0 | X46: =IFERROR(VLOOKUP(E46,Sheet2!$AG$1:$AH$975,2,FALSE),0) -> 0 | Z46: =IFERROR(VLOOKUP(F46,Sheet2!$AA$1:$AB$975,2,FALSE),0) -> 0 | AA46: =IFERROR(VLOOKUP(F46,Sheet2!$AC$1:$AD$975,2,FALSE),0) -> 0 | AB46: =IFERROR(VLOOKUP(F46,Sheet2!$AE$2:$AF$6539,2,FALSE),0) -> 0 | AC46: =IFERROR(VLOOKUP(F46,Sheet2!$AG$2:$AH$6539,2,FALSE),0) -> 0 | AE46: 0 | AF46: 0 | AG46: 0 | AH46: 0 | AI46: 0 | AJ46: =SUM(AE46+AI46) -> 0 | AK46: =SUM(AJ46*O46) -> 0 | AL46: 0 | AM46: 0
A47: GoBros | B47: 46173 | D47: 048323187718 | E47: WIGF1140_052_bla_2 | F47: ZZWIGF1140_052_bla_2 | G47: #N/A | H47: FBM Only | I47: F1140 | J47: Wigwam At Work Steel Toe Heavyweight Socks | K47: Black | L47: Large | O47: 6.912 | R47: =IFERROR(VLOOKUP(E47,Sheet6!$A$2:$B$500,2,FALSE),0) -> 0 | S47: =IFERROR(VLOOKUP(E47,Sheet6!$C$2:$D$35017,2,FALSE),0) -> 0 | U47: =IFERROR(VLOOKUP(E47,Sheet2!$AA$1:$AB$975,2,FALSE),0) -> 0 | V47: =IFERROR(VLOOKUP(E47,Sheet2!$AC$1:$AD$975,2,FALSE),0) -> 0 | W47: =IFERROR(VLOOKUP(E47,Sheet2!$AE$1:$AF$975,2,FALSE),0) -> 0 | X47: =IFERROR(VLOOKUP(E47,Sheet2!$AG$1:$AH$975,2,FALSE),0) -> 0 | Z47: =IFERROR(VLOOKUP(F47,Sheet2!$AA$1:$AB$975,2,FALSE),0) -> 0 | AA47: =IFERROR(VLOOKUP(F47,Sheet2!$AC$1:$AD$975,2,FALSE),0) -> 0 | AB47: =IFERROR(VLOOKUP(F47,Sheet2!$AE$2:$AF$6539,2,FALSE),0) -> 0 | AC47: =IFERROR(VLOOKUP(F47,Sheet2!$AG$2:$AH$6539,2,FALSE),0) -> 0 | AE47: 25 | AF47: 0 | AG47: 0 | AH47: 0 | AI47: 0 | AJ47: =SUM(AE47+AI47) -> 25 | AK47: =SUM(AJ47*O47) -> 172.8 | AL47: 0 | AM47: 0
A48: GoBros | B48: 46173 | D48: 048323187725 | E48: WIGF1140_052_bla_3 | F48: ZZWIGF1140_052_bla_3 | G48: #N/A | H48: FBM Only | I48: F1140 | J48: Wigwam At Work Steel Toe Heavyweight Socks | K48: Black | L48: X-Large | O48: 6.912 | R48: =IFERROR(VLOOKUP(E48,Sheet6!$A$2:$B$500,2,FALSE),0) -> 0 | S48: =IFERROR(VLOOKUP(E48,Sheet6!$C$2:$D$35017,2,FALSE),0) -> 0 | U48: =IFERROR(VLOOKUP(E48,Sheet2!$AA$1:$AB$975,2,FALSE),0) -> 0 | V48: =IFERROR(VLOOKUP(E48,Sheet2!$AC$1:$AD$975,2,FALSE),0) -> 0 | W48: =IFERROR(VLOOKUP(E48,Sheet2!$AE$1:$AF$975,2,FALSE),0) -> 0 | X48: =IFERROR(VLOOKUP(E48,Sheet2!$AG$1:$AH$975,2,FALSE),0) -> 0 | Z48: =IFERROR(VLOOKUP(F48,Sheet2!$AA$1:$AB$975,2,FALSE),0) -> 0 | AA48: =IFERROR(VLOOKUP(F48,Sheet2!$AC$1:$AD$975,2,FALSE),0) -> 0 | AB48: =IFERROR(VLOOKUP(F48,Sheet2!$AE$2:$AF$6539,2,FALSE),0) -> 0 | AC48: =IFERROR(VLOOKUP(F48,Sheet2!$AG$2:$AH$6539,2,FALSE),0) -> 0 | AE48: 0 | AF48: 0 | AG48: 0 | AH48: 0 | AI48: 0 | AJ48: =SUM(AE48+AI48) -> 0 | AK48: =SUM(AJ48*O48) -> 0 | AL48: 0 | AM48: 0
... A75: GoBros | B75: 46173 | D75: 048323426411 | E75: WIGF1364_052_blk_1 | F75: ZZWIGF1364_052_blk_1 | G75: #N/A | H75: FBM Only | I75: F1364 | J75: Wigwam Diabetic Sport Quarter Midweight Socks | K75: Black | L75: Large | O75: 6.48 | R75: =IFERROR(VLOOKUP(E75,Sheet6!$A$2:$B$500,2,FALSE),0) -> 2 | S75: =IFERROR(VLOOKUP(E75,Sheet6!$C$2:$D$35017,2,FALSE),0) -> 27.01 | U75: =IFERROR(VLOOKUP(E75,Sheet2!$AA$1:$AB$975,2,FALSE),0) -> 6 | V75: =IFERROR(VLOOKUP(E75,Sheet2!$AC$1:$AD$975,2,FALSE),0) -> 90 | W75: =IFERROR(VLOOKUP(E75,Sheet2!$AE$1:$AF$975,2,FALSE),0) -> 34 | X75: =IFERROR(VLOOKUP(E75,Sheet2!$AG$1:$AH$975,2,FALSE),0) -> 0.9783 | Z75: =IFERROR(VLOOKUP(F75,Sheet2!$AA$1:$AB$975,2,FALSE),0) -> 0 | AA75: =IFERROR(VLOOKUP(F75,Sheet2!$AC$1:$AD$975,2,FALSE),0) -> 0 | AB75: =IFERROR(VLOOKUP(F75,Sheet2!$AE$2:$AF$6539,2,FALSE),0) -> 0 | AC75: =IFERROR(VLOOKUP(F75,Sheet2!$AG$2:$AH$6539,2,FALSE),0) -> 0 | AE75: 87 | AF75: 0 | AG75: 0 | AH75: 0 | AI75: 0 | AJ75: =SUM(AE75+AI75) -> 87 | AK75: =SUM(AJ75*O75) -> 563.76 | AL75: 0 | AM75: 0
A76: GoBros | B76: 46173 | D76: 048323426428 | E76: WIGF1364_052_blk_2 | F76: ZZWIGF1364_052_blk_2 | G76: B09MBVPZBH | H76: FBA | I76: F1364 | J76: Wigwam Diabetic Sport Quarter Midweight Socks | K76: Black | L76: X-Large | O76: 6.48 | R76: =IFERROR(VLOOKUP(E76,Sheet6!$A$2:$B$500,2,FALSE),0) -> 6 | S76: =IFERROR(VLOOKUP(E76,Sheet6!$C$2:$D$35017,2,FALSE),0) -> 90 | U76: =IFERROR(VLOOKUP(E76,Sheet2!$AA$1:$AB$975,2,FALSE),0) -> 23 | V76: =IFERROR(VLOOKUP(E76,Sheet2!$AC$1:$AD$975,2,FALSE),0) -> 345 | W76: =IFERROR(VLOOKUP(E76,Sheet2!$AE$1:$AF$975,2,FALSE),0) -> 50 | X76: =IFERROR(VLOOKUP(E76,Sheet2!$AG$1:$AH$975,2,FALSE),0) -> 0.9848 | Z76: =IFERROR(VLOOKUP(F76,Sheet2!$AA$1:$AB$975,2,FALSE),0) -> 0 | AA76: =IFERROR(VLOOKUP(F76,Sheet2!$AC$1:$AD$975,2,FALSE),0) -> 0 | AB76: =IFERROR(VLOOKUP(F76,Sheet2!$AE$2:$AF$6539,2,FALSE),0) -> 0 | AC76: =IFERROR(VLOOKUP(F76,Sheet2!$AG$2:$AH$6539,2,FALSE),0) -> 0 | AE76: 106 | AF76: 0 | AG76: 0 | AH76: 0 | AI76: 0 | AJ76: =SUM(AE76+AI76) -> 106 | AK76: =SUM(AJ76*O76) -> 686.88 | AL76: 0 | AM76: 0
A77: GoBros | B77: 46173 | D77: 048323666183 | E77: WIGF1446_586_nvy_0 | F77: ZZWIGF1446_586_nvy_0 | G77: #N/A | H77: FBA | I77: F1446 | J77: Wigwam USA Snow Over-The-Calf Lightweight Socks | K77: Navy | L77: Small | O77: 11.232 | R77: =IFERROR(VLOOKUP(E77,Sheet6!$A$2:$B$500,2,FALSE),0) -> 0 | S77: =IFERROR(VLOOKUP(E77,Sheet6!$C$2:$D$35017,2,FALSE),0) -> 0 | U77: =IFERROR(VLOOKUP(E77,Sheet2!$AA$1:$AB$975,2,FALSE),0) -> 0 | V77: =IFERROR(VLOOKUP(E77,Sheet2!$AC$1:$AD$975,2,FALSE),0) -> 0 | W77: =IFERROR(VLOOKUP(E77,Sheet2!$AE$1:$AF$975,2,FALSE),0) -> 0 | X77: =IFERROR(VLOOKUP(E77,Sheet2!$AG$1:$AH$975,2,FALSE),0) -> 0 | Z77: =IFERROR(VLOOKUP(F77,Sheet2!$AA$1:$AB$975,2,FALSE),0) -> 0 | AA77: =IFERROR(VLOOKUP(F77,Sheet2!$AC$1:$AD$975,2,FALSE),0) -> 0 | AB77: =IFERROR(VLOOKUP(F77,Sheet2!$AE$2:$AF$6539,2,FALSE),0) -> 0 | AC77: =IFERROR(VLOOKUP(F77,Sheet2!$AG$2:$AH$6539,2,FALSE),0) -> 0 | AE77: 3 | AF77: 6 | AG77: 0 | AH77: 0 | AI77: 6 | AJ77: =SUM(AE77+AI77) -> 9 | AK77: =SUM(AJ77*O77) -> 101.088 | AL77: 0 | AM77: 0
A78: GoBros | B78: 46173 | D78: 048323666190 | E78: WIGF1446_586_nvy_1 | F78: ZZWIGF1446_586_nvy_1 | G78: #N/A | H78: FBA | I78: F1446 | J78: Wigwam USA Snow Over-The-Calf Lightweight Socks | K78: Navy | L78: Medium | O78: 11.232 | R78: =IFERROR(VLOOKUP(E78,Sheet6!$A$2:$B$500,2,FALSE),0) -> 0 | S78: =IFERROR(VLOOKUP(E78,Sheet6!$C$2:$D$35017,2,FALSE),0) -> 0 | U78: =IFERROR(VLOOKUP(E78,Sheet2!$AA$1:$AB$975,2,FALSE),0) -> 0 | V78: =IFERROR(VLOOKUP(E78,Sheet2!$AC$1:$AD$975,2,FALSE),0) -> 0 | W78: =IFERROR(VLOOKUP(E78,Sheet2!$AE$1:$AF$975,2,FALSE),0) -> 0 | X78: =IFERROR(VLOOKUP(E78,Sheet2!$AG$1:$AH$975,2,FALSE),0) -> 0 | Z78: =IFERROR(VLOOKUP(F78,Sheet2!$AA$1:$AB$975,2,FALSE),0) -> 0 | AA78: =IFERROR(VLOOKUP(F78,Sheet2!$AC$1:$AD$975,2,FALSE),0) -> 0 | AB78: =IFERROR(VLOOKUP(F78,Sheet2!$AE$2:$AF$6539,2,FALSE),0) -> 0 | AC78: =IFERROR(VLOOKUP(F78,Sheet2!$AG$2:$AH$6539,2,FALSE),0) -> 0 | AE78: 12 | AF78: 2 | AG78: 0 | AH78: 0 | AI78: 2 | AJ78: =SUM(AE78+AI78) -> 14 | AK78: =SUM(AJ78*O78) -> 157.248 | AL78: 0 | AM78: 0
A79: GoBros | B79: 46173 | D79: 048323666206 | E79: WIGF1446_586_nvy_2 | F79: ZZWIGF1446_586_nvy_2 | G79: #N/A | H79: FBA | I79: F1446 | J79: Wigwam USA Snow Over-The-Calf Lightweight Socks | K79: Navy | L79: Large | O79: 11.232 | R79: =IFERROR(VLOOKUP(E79,Sheet6!$A$2:$B$500,2,FALSE),0) -> 0 | S79: =IFERROR(VLOOKUP(E79,Sheet6!$C$2:$D$35017,2,FALSE),0) -> 0 | U79: =IFERROR(VLOOKUP(E79,Sheet2!$AA$1:$AB$975,2,FALSE),0) -> 0 | V79: =IFERROR(VLOOKUP(E79,Sheet2!$AC$1:$AD$975,2,FALSE),0) -> 0 | W79: =IFERROR(VLOOKUP(E79,Sheet2!$AE$1:$AF$975,2,FALSE),0) -> 0 | X79: =IFERROR(VLOOKUP(E79,Sheet2!$AG$1:$AH$975,2,FALSE),0) -> 0 | Z79: =IFERROR(VLOOKUP(F79,Sheet2!$AA$1:$AB$975,2,FALSE),0) -> 0 | AA79: =IFERROR(VLOOKUP(F79,Sheet2!$AC$1:$AD$975,2,FALSE),0) -> 0 | AB79: =IFERROR(VLOOKUP(F79,Sheet2!$AE$2:$AF$6539,2,FALSE),0) -> 0 | AC79: =IFERROR(VLOOKUP(F79,Sheet2!$AG$2:$AH$6539,2,FALSE),0) -> 0 | AE79: 2 | AF79: 22 | AG79: 0 | AH79: 1 | AI79: 23 | AJ79: =SUM(AE79+AI79) -> 25 | AK79: =SUM(AJ79*O79) -> 280.8 | AL79: 0 | AM79: 0
A80: GoBros | B80: 46173 | D80: 048323666213 | E80: WIGF1446_586_nvy_3 | F80: ZZWIGF1446_586_nvy_3 | G80: #N/A | H80: FBA | I80: F1446 | J80: Wigwam USA Snow Over-The-Calf Lightweight Socks | K80: Navy | L80: X-Large | O80: 11.232 | R80: =IFERROR(VLOOKUP(E80,Sheet6!$A$2:$B$500,2,FALSE),0) -> 0 | S80: =IFERROR(VLOOKUP(E80,Sheet6!$C$2:$D$35017,2,FALSE),0) -> 0 | U80: =IFERROR(VLOOKUP(E80,Sheet2!$AA$1:$AB$975,2,FALSE),0) -> 0 | V80: =IFERROR(VLOOKUP(E80,Sheet2!$AC$1:$AD$975,2,FALSE),0) -> 0 | W80: =IFERROR(VLOOKUP(E80,Sheet2!$AE$1:$AF$975,2,FALSE),0) -> 0 | X80: =IFERROR(VLOOKUP(E80,Sheet2!$AG$1:$AH$975,2,FALSE),0) -> 0 | Z80: =IFERROR(VLOOKUP(F80,Sheet2!$AA$1:$AB$975,2,FALSE),0) -> 0 | AA80: =IFERROR(VLOOKUP(F80,Sheet2!$AC$1:$AD$975,2,FALSE),0) -> 0 | AB80: =IFERROR(VLOOKUP(F80,Sheet2!$AE$2:$AF$6539,2,FALSE),0) -> 0 | AC80: =IFERROR(VLOOKUP(F80,Sheet2!$AG$2:$AH$6539,2,FALSE),0) -> 0 | AE80: 12 | AF80: 20 | AG80: 0 | AH80: 1 | AI80: 21 | AJ80: =SUM(AE80+AI80) -> 33 | AK80: =SUM(AJ80*O80) -> 370.656 | AL80: 0 | AM80: 0
A81: GoBros | B81: 46173 | D81: 048323666930 | E81: WIGF1453_072_gry_1 | F81: ZZWIGF1453_072_gry_1 | G81: #N/A | H81: FBA | I81: F1453 | J81: Wigwam Snow Shield Over-The-Calf Socks | K81: Grey | L81: Medium | O81: 11.232 | R81: =IFERROR(VLOOKUP(E81,Sheet6!$A$2:$B$500,2,FALSE),0) -> 0 | S81: =IFERROR(VLOOKUP(E81,Sheet6!$C$2:$D$35017,2,FALSE),0) -> 0 | U81: =IFERROR(VLOOKUP(E81,Sheet2!$AA$1:$AB$975,2,FALSE),0) -> 0 | V81: =IFERROR(VLOOKUP(E81,Sheet2!$AC$1:$AD$975,2,FALSE),0) -> 0 | W81: =IFERROR(VLOOKUP(E81,Sheet2!$AE$1:$AF$975,2,FALSE),0) -> 0 | X81: =IFERROR(VLOOKUP(E81,Sheet2!$AG$1:$AH$975,2,FALSE),0) -> 0 | Z81: =IFERROR(VLOOKUP(F81,Sheet2!$AA$1:$AB$975,2,FALSE),0) -> 0 | AA81: =IFERROR(VLOOKUP(F81,Sheet2!$AC$1:$AD$975,2,FALSE),0) -> 0 | AB81: =IFERROR(VLOOKUP(F81,Sheet2!$AE$2:$AF$6539,2,FALSE),0) -> 0 | AC81: =IFERROR(VLOOKUP(F81,Sheet2!$AG$2:$AH$6539,2,FALSE),0) -> 0 | AE81: 11 | AF81: 2 | AG81: 0 | AH81: 0 | AI81: 2 | AJ81: =SUM(AE81+AI81) -> 13 | AK81: =SUM(AJ81*O81) -> 146.016 | AL81: 6 | AM81: 0
A82: GoBros | B82: 46173 | D82: 048323666947 | E82: WIGF1453_072_gry_2 | F82: ZZWIGF1453_072_gry_2 | G82: #N/A | H82: FBA | I82: F1453 | J82: Wigwam Snow Shield Over-The-Calf Socks | K82: Grey | L82: Large | O82: 11.232 | R82: =IFERROR(VLOOKUP(E82,Sheet6!$A$2:$B$500,2,FALSE),0) -> 0 | S82: =IFERROR(VLOOKUP(E82,Sheet6!$C$2:$D$35017,2,FALSE),0) -> 0 | U82: =IFERROR(VLOOKUP(E82,Sheet2!$AA$1:$AB$975,2,FALSE),0) -> 0 | V82: =IFERROR(VLOOKUP(E82,Sheet2!$AC$1:$AD$975,2,FALSE),0) -> 0 | W82: =IFERROR(VLOOKUP(E82,Sheet2!$AE$1:$AF$975,2,FALSE),0) -> 0 | X82: =IFERROR(VLOOKUP(E82,Sheet2!$AG$1:$AH$975,2,FALSE),0) -> 0 | Z82: =IFERROR(VLOOKUP(F82,Sheet2!$AA$1:$AB$975,2,FALSE),0) -> 0 | AA82: =IFERROR(VLOOKUP(F82,Sheet2!$AC$1:$AD$975,2,FALSE),0) -> 0 | AB82: =IFERROR(VLOOKUP(F82,Sheet2!$AE$2:$AF$6539,2,FALSE),0) -> 0 | AC82: =IFERROR(VLOOKUP(F82,Sheet2!$AG$2:$AH$6539,2,FALSE),0) -> 0 | AE82: 10 | AF82: 0 | AG82: 0 | AH82: 0 | AI82: 0 | AJ82: =SUM(AE82+AI82) -> 10 | AK82: =SUM(AJ82*O82) -> 112.32 | AL82: 6 | AM82: 12
A83: GoBros | B83: 46173 | D83: 048323666954 | E83: WIGF1453_072_gry_3 | F83: ZZWIGF1453_072_gry_3 | G83: #N/A | H83: FBM Only | I83: F1453 | J83: Wigwam Snow Shield Over-The-Calf Socks | K83: Grey | L83: X-Large | O83: 11.232 | R83: =IFERROR(VLOOKUP(E83,Sheet6!$A$2:$B$500,2,FALSE),0) -> 0 | S83: =IFERROR(VLOOKUP(E83,Sheet6!$C$2:$D$35017,2,FALSE),0) -> 0 | U83: =IFERROR(VLOOKUP(E83,Sheet2!$AA$1:$AB$975,2,FALSE),0) -> 0 | V83: =IFERROR(VLOOKUP(E83,Sheet2!$AC$1:$AD$975,2,FALSE),0) -> 0 | W83: =IFERROR(VLOOKUP(E83,Sheet2!$AE$1:$AF$975,2,FALSE),0) -> 0 | X83: =IFERROR(VLOOKUP(E83,Sheet2!$AG$1:$AH$975,2,FALSE),0) -> 0 | Z83: =IFERROR(VLOOKUP(F83,Sheet2!$AA$1:$AB$975,2,FALSE),0) -> 0 | AA83: =IFERROR(VLOOKUP(F83,Sheet2!$AC$1:$AD$975,2,FALSE),0) -> 0 | AB83: =IFERROR(VLOOKUP(F83,Sheet2!$AE$2:$AF$6539,2,FALSE),0) -> 0 | AC83: =IFERROR(VLOOKUP(F83,Sheet2!$AG$2:$AH$6539,2,FALSE),0) -> 0 | AE83: 29 | AF83: 10 | AG83: 0 | AH83: 0 | AI83: 10 | AJ83: =SUM(AE83+AI83) -> 39 | AK83: =SUM(AJ83*O83) -> 438.048 | AL83: 0 | AM83: 0
A84: GoBros | B84: 46173 | D84: 048323656634 | E84: WIGF1702_072_gry_0 | F84: ZZWIGF1702_072_gry_0 | G84: #N/A | H84: FBM Only | I84: F1702 | J84: Wigwam Axiom Lightweight No Show Socks | K84: Grey | L84: Small | O84: 7.776 | R84: =IFERROR(VLOOKUP(E84,Sheet6!$A$2:$B$500,2,FALSE),0) -> 0 | S84: =IFERROR(VLOOKUP(E84,Sheet6!$C$2:$D$35017,2,FALSE),0) -> 0 | U84: =IFERROR(VLOOKUP(E84,Sheet2!$AA$1:$AB$975,2,FALSE),0) -> 0 | V84: =IFERROR(VLOOKUP(E84,Sheet2!$AC$1:$AD$975,2,FALSE),0) -> 0 | W84: =IFERROR(VLOOKUP(E84,Sheet2!$AE$1:$AF$975,2,FALSE),0) -> 0 | X84: =IFERROR(VLOOKUP(E84,Sheet2!$AG$1:$AH$975,2,FALSE),0) -> 0 | Z84: =IFERROR(VLOOKUP(F84,Sheet2!$AA$1:$AB$975,2,FALSE),0) -> 0 | AA84: =IFERROR(VLOOKUP(F84,Sheet2!$AC$1:$AD$975,2,FALSE),0) -> 0 | AB84: =IFERROR(VLOOKUP(F84,Sheet2!$AE$2:$AF$6539,2,FALSE),0) -> 0 | AC84: =IFERROR(VLOOKUP(F84,Sheet2!$AG$2:$AH$6539,2,FALSE),0) -> 0 | AE84: 0 | AF84: 0 | AG84: 0 | AH84: 0 | AI84: 0 | AJ84: =SUM(AE84+AI84) -> 0 | AK84: =SUM(AJ84*O84) -> 0 | AL84: 0 | AM84: 0
A85: GoBros | B85: 46173 | D85: 048323656665 | E85: WIGF1702_072_gry_3 | F85: ZZWIGF1702_072_gry_3 | G85: #N/A | H85: FBM Only | I85: F1702 | J85: Wigwam Axiom Lightweight No Show Socks | K85: Grey | L85: X-Large | O85: 7.776 | R85: =IFERROR(VLOOKUP(E85,Sheet6!$A$2:$B$500,2,FALSE),0) -> 0 | S85: =IFERROR(VLOOKUP(E85,Sheet6!$C$2:$D$35017,2,FALSE),0) -> 0 | U85: =IFERROR(VLOOKUP(E85,Sheet2!$AA$1:$AB$975,2,FALSE),0) -> 0 | V85: =IFERROR(VLOOKUP(E85,Sheet2!$AC$1:$AD$975,2,FALSE),0) -> 0 | W85: =IFERROR(VLOOKUP(E85,Sheet2!$AE$1:$AF$975,2,FALSE),0) -> 0 | X85: =IFERROR(VLOOKUP(E85,Sheet2!$AG$1:$AH$975,2,FALSE),0) -> 0 | Z85: =IFERROR(VLOOKUP(F85,Sheet2!$AA$1:$AB$975,2,FALSE),0) -> 0 | AA85: =IFERROR(VLOOKUP(F85,Sheet2!$AC$1:$AD$975,2,FALSE),0) -> 0 | AB85: =IFERROR(VLOOKUP(F85,Sheet2!$AE$2:$AF$6539,2,FALSE),0) -> 0 | AC85: =IFERROR(VLOOKUP(F85,Sheet2!$AG$2:$AH$6539,2,FALSE),0) -> 0 | AE85: 0 | AF85: 0 | AG85: 0 | AH85: 0 | AI85: 0 | AJ85: =SUM(AE85+AI85) -> 0 | AK85: =SUM(AJ85*O85) -> 0 | AL85: 0 | AM85: 0
A86: GoBros | B86: 46173 | D86: 048323656689 | E86: WIGF1702_625_blk_1 | F86: ZZWIGF1702_625_blk_1 | G86: #N/A | H86: FBM Only | I86: F1702 | J86: Wigwam Axiom Lightweight No Show Socks | K86: Black Sand | L86: Medium | O86: 7.776 | R86: =IFERROR(VLOOKUP(E86,Sheet6!$A$2:$B$500,2,FALSE),0) -> 0 | S86: =IFERROR(VLOOKUP(E86,Sheet6!$C$2:$D$35017,2,FALSE),0) -> 0 | U86: =IFERROR(VLOOKUP(E86,Sheet2!$AA$1:$AB$975,2,FALSE),0) -> 0 | V86: =IFERROR(VLOOKUP(E86,Sheet2!$AC$1:$AD$975,2,FALSE),0) -> 0 | W86: =IFERROR(VLOOKUP(E86,Sheet2!$AE$1:$AF$975,2,FALSE),0) -> 0 | X86: =IFERROR(VLOOKUP(E86,Sheet2!$AG$1:$AH$975,2,FALSE),0) -> 0 | Z86: =IFERROR(VLOOKUP(F86,Sheet2!$AA$1:$AB$975,2,FALSE),0) -> 0 | AA86: =IFERROR(VLOOKUP(F86,Sheet2!$AC$1:$AD$975,2,FALSE),0) -> 0 | AB86: =IFERROR(VLOOKUP(F86,Sheet2!$AE$2:$AF$6539,2,FALSE),0) -> 0 | AC86: =IFERROR(VLOOKUP(F86,Sheet2!$AG$2:$AH$6539,2,FALSE),0) -> 0 | AE86: 0 | AF86: 0 | AG86: 0 | AH86: 0 | AI86: 0 | AJ86: =SUM(AE86+AI86) -> 0 | AK86: =SUM(AJ86*O86) -> 0 | AL86: 0 | AM86: 0
A87: GoBros | B87: 46173 | D87: 048323656696 | E87: WIGF1702_625_blk_2 | F87: ZZWIGF1702_625_blk_2 | G87: #N/A | H87: FBM Only | I87: F1702 | J87: Wigwam Axiom Lightweight No Show Socks | K87: Black Sand | L87: Large | O87: 7.776 | R87: =IFERROR(VLOOKUP(E87,Sheet6!$A$2:$B$500,2,FALSE),0) -> 0 | S87: =IFERROR(VLOOKUP(E87,Sheet6!$C$2:$D$35017,2,FALSE),0) -> 0 | U87: =IFERROR(VLOOKUP(E87,Sheet2!$AA$1:$AB$975,2,FALSE),0) -> 0 | V87: =IFERROR(VLOOKUP(E87,Sheet2!$AC$1:$AD$975,2,FALSE),0) -> 0 | W87: =IFERROR(VLOOKUP(E87,Sheet2!$AE$1:$AF$975,2,FALSE),0) -> 0 | X87: =IFERROR(VLOOKUP(E87,Sheet2!$AG$1:$AH$975,2,FALSE),0) -> 0 | Z87: =IFERROR(VLOOKUP(F87,Sheet2!$AA$1:$AB$975,2,FALSE),0) -> 0 | AA87: =IFERROR(VLOOKUP(F87,Sheet2!$AC$1:$AD$975,2,FALSE),0) -> 0 | AB87: =IFERROR(VLOOKUP(F87,Sheet2!$AE$2:$AF$6539,2,FALSE),0) -> 0 | AC87: =IFERROR(VLOOKUP(F87,Sheet2!$AG$2:$AH$6539,2,FALSE),0) -> 0 | AE87: 0 | AF87: 0 | AG87: 0 | AH87: 0 | AI87: 0 | AJ87: =SUM(AE87+AI87) -> 0 | AK87: =SUM(AJ87*O87) -> 0 | AL87: 0 | AM87: 0
A88: GoBros | B88: 46173 | D88: 048323656726 | E88: WIGF1702_676_cat_1 | F88: ZZWIGF1702_676_cat_1 | G88: #N/A | H88: FBM Only | I88: F1702 | J88: Wigwam Axiom Lightweight No Show Socks | K88: Catawba Grape | L88: Medium | O88: 7.776 | R88: =IFERROR(VLOOKUP(E88,Sheet6!$A$2:$B$500,2,FALSE),0) -> 0 | S88: =IFERROR(VLOOKUP(E88,Sheet6!$C$2:$D$35017,2,FALSE),0) -> 0 | U88: =IFERROR(VLOOKUP(E88,Sheet2!$AA$1:$AB$975,2,FALSE),0) -> 0 | V88: =IFERROR(VLOOKUP(E88,Sheet2!$AC$1:$AD$975,2,FALSE),0) -> 0 | W88: =IFERROR(VLOOKUP(E88,Sheet2!$AE$1:$AF$975,2,FALSE),0) -> 0 | X88: =IFERROR(VLOOKUP(E88,Sheet2!$AG$1:$AH$975,2,FALSE),0) -> 0 | Z88: =IFERROR(VLOOKUP(F88,Sheet2!$AA$1:$AB$975,2,FALSE),0) -> 0 | AA88: =IFERROR(VLOOKUP(F88,Sheet2!$AC$1:$AD$975,2,FALSE),0) -> 0 | AB88: =IFERROR(VLOOKUP(F88,Sheet2!$AE$2:$AF$6539,2,FALSE),0) -> 0 | AC88: =IFERROR(VLOOKUP(F88,Sheet2!$AG$2:$AH$6539,2,FALSE),0) -> 0 | AE88: 0 | AF88: 0 | AG88: 0 | AH88: 0 | AI88: 0 | AJ88: =SUM(AE88+AI88) -> 0 | AK88: =SUM(AJ88*O88) -> 0 | AL88: 0 | AM88: 0
... A112: GoBros | B112: 46173 | D112: 048323437004 | E112: WIGF2062_792_blk_2 | F112: ZZWIGF2062_792_blk_2 | G112: #N/A | H112: FBA | I112: F2062 | J112: Wigwam Diabetic Thermal Crew Heavyweight Wool Socks | K112: Grey/Black | L112: Large | O112: 8.208 | R112: =IFERROR(VLOOKUP(E112,Sheet6!$A$2:$B$500,2,FALSE),0) -> 0 | S112: =IFERROR(VLOOKUP(E112,Sheet6!$C$2:$D$35017,2,FALSE),0) -> 0 | U112: =IFERROR(VLOOKUP(E112,Sheet2!$AA$1:$AB$975,2,FALSE),0) -> 0 | V112: =IFERROR(VLOOKUP(E112,Sheet2!$AC$1:$AD$975,2,FALSE),0) -> 0 | W112: =IFERROR(VLOOKUP(E112,Sheet2!$AE$1:$AF$975,2,FALSE),0) -> 0 | X112: =IFERROR(VLOOKUP(E112,Sheet2!$AG$1:$AH$975,2,FALSE),0) -> 0 | Z112: =IFERROR(VLOOKUP(F112,Sheet2!$AA$1:$AB$975,2,FALSE),0) -> 0 | AA112: =IFERROR(VLOOKUP(F112,Sheet2!$AC$1:$AD$975,2,FALSE),0) -> 0 | AB112: =IFERROR(VLOOKUP(F112,Sheet2!$AE$2:$AF$6539,2,FALSE),0) -> 0 | AC112: =IFERROR(VLOOKUP(F112,Sheet2!$AG$2:$AH$6539,2,FALSE),0) -> 0 | AE112: 12 | AF112: 26 | AG112: 0 | AH112: 0 | AI112: 26 | AJ112: =SUM(AE112+AI112) -> 38 | AK112: =SUM(AJ112*O112) -> 311.904 | AL112: 0 | AM112: 0
A113: GoBros | B113: 46173 | D113: 048323437011 | E113: WIGF2062_792_blk_3 | F113: ZZWIGF2062_792_blk_3 | G113: B0BP21C43L | H113: FBA | I113: F2062 | J113: Wigwam Diabetic Thermal Crew Heavyweight Wool Socks | K113: Grey/Black | L113: X-Large | O113: 8.208 | R113: =IFERROR(VLOOKUP(E113,Sheet6!$A$2:$B$500,2,FALSE),0) -> 2 | S113: =IFERROR(VLOOKUP(E113,Sheet6!$C$2:$D$35017,2,FALSE),0) -> 36.1 | U113: =IFERROR(VLOOKUP(E113,Sheet2!$AA$1:$AB$975,2,FALSE),0) -> 9 | V113: =IFERROR(VLOOKUP(E113,Sheet2!$AC$1:$AD$975,2,FALSE),0) -> 171 | W113: =IFERROR(VLOOKUP(E113,Sheet2!$AE$1:$AF$975,2,FALSE),0) -> 62 | X113: =IFERROR(VLOOKUP(E113,Sheet2!$AG$1:$AH$975,2,FALSE),0) -> 0 | Z113: =IFERROR(VLOOKUP(F113,Sheet2!$AA$1:$AB$975,2,FALSE),0) -> 0 | AA113: =IFERROR(VLOOKUP(F113,Sheet2!$AC$1:$AD$975,2,FALSE),0) -> 0 | AB113: =IFERROR(VLOOKUP(F113,Sheet2!$AE$2:$AF$6539,2,FALSE),0) -> 0 | AC113: =IFERROR(VLOOKUP(F113,Sheet2!$AG$2:$AH$6539,2,FALSE),0) -> 0 | AE113: 8 | AF113: 0 | AG113: 0 | AH113: 0 | AI113: 0 | AJ113: =SUM(AE113+AI113) -> 8 | AK113: =SUM(AJ113*O113) -> 65.664 | AL113: 54 | AM113: 30
A114: GoBros | B114: 46173 | D114: 048323023283 | E114: WIGF2153_51_whi_1 | F114: ZZWIGF2153_51_whi_1 | G114: B09F9C4D58 | H114: FBA | I114: F2153 | J114: Wigwam Gobi Liner Ultra-Lightweight Crew Socks | K114: White | L114: Medium | O114: 4.95 | R114: =IFERROR(VLOOKUP(E114,Sheet6!$A$2:$B$500,2,FALSE),0) -> 0 | S114: =IFERROR(VLOOKUP(E114,Sheet6!$C$2:$D$35017,2,FALSE),0) -> 0 | U114: =IFERROR(VLOOKUP(E114,Sheet2!$AA$1:$AB$975,2,FALSE),0) -> 0 | V114: =IFERROR(VLOOKUP(E114,Sheet2!$AC$1:$AD$975,2,FALSE),0) -> 0 | W114: =IFERROR(VLOOKUP(E114,Sheet2!$AE$1:$AF$975,2,FALSE),0) -> 0 | X114: =IFERROR(VLOOKUP(E114,Sheet2!$AG$1:$AH$975,2,FALSE),0) -> 0 | Z114: =IFERROR(VLOOKUP(F114,Sheet2!$AA$1:$AB$975,2,FALSE),0) -> 0 | AA114: =IFERROR(VLOOKUP(F114,Sheet2!$AC$1:$AD$975,2,FALSE),0) -> 0 | AB114: =IFERROR(VLOOKUP(F114,Sheet2!$AE$2:$AF$6539,2,FALSE),0) -> 0 | AC114: =IFERROR(VLOOKUP(F114,Sheet2!$AG$2:$AH$6539,2,FALSE),0) -> 0 | AE114: 0 | AF114: 0 | AG114: 0 | AH114: 0 | AI114: 0 | AJ114: =SUM(AE114+AI114) -> 0 | AK114: =SUM(AJ114*O114) -> 0 | AL114: 0 | AM114: 0
A115: GoBros | B115: 46173 | D115: 048323023276 | E115: WIGF2153_51_whi_2 | F115: ZZWIGF2153_51_whi_2 | G115: #N/A | H115: FBM Only | I115: F2153 | J115: Wigwam Gobi Liner Ultra-Lightweight Crew Socks | K115: White | L115: Large | O115: 4.95 | R115: =IFERROR(VLOOKUP(E115,Sheet6!$A$2:$B$500,2,FALSE),0) -> 6 | S115: =IFERROR(VLOOKUP(E115,Sheet6!$C$2:$D$35017,2,FALSE),0) -> 56.1 | U115: =IFERROR(VLOOKUP(E115,Sheet2!$AA$1:$AB$975,2,FALSE),0) -> 13 | V115: =IFERROR(VLOOKUP(E115,Sheet2!$AC$1:$AD$975,2,FALSE),0) -> 143 | W115: =IFERROR(VLOOKUP(E115,Sheet2!$AE$1:$AF$975,2,FALSE),0) -> 29 | X115: =IFERROR(VLOOKUP(E115,Sheet2!$AG$1:$AH$975,2,FALSE),0) -> 1 | Z115: =IFERROR(VLOOKUP(F115,Sheet2!$AA$1:$AB$975,2,FALSE),0) -> 0 | AA115: =IFERROR(VLOOKUP(F115,Sheet2!$AC$1:$AD$975,2,FALSE),0) -> 0 | AB115: =IFERROR(VLOOKUP(F115,Sheet2!$AE$2:$AF$6539,2,FALSE),0) -> 0 | AC115: =IFERROR(VLOOKUP(F115,Sheet2!$AG$2:$AH$6539,2,FALSE),0) -> 0 | AE115: 0 | AF115: 0 | AG115: 0 | AH115: 0 | AI115: 0 | AJ115: =SUM(AE115+AI115) -> 0 | AK115: =SUM(AJ115*O115) -> 0 | AL115: 0 | AM115: 0
A116: GoBros | B116: 46173 | D116: 048323023306 | E116: WIGF2153_51_whi_3 | F116: ZZWIGF2153_51_whi_3 | G116: #N/A | H116: FBM Only | I116: F2153 | J116: Wigwam Gobi Liner Ultra-Lightweight Crew Socks | K116: White | L116: X-Large | O116: 4.95 | R116: =IFERROR(VLOOKUP(E116,Sheet6!$A$2:$B$500,2,FALSE),0) -> 0 | S116: =IFERROR(VLOOKUP(E116,Sheet6!$C$2:$D$35017,2,FALSE),0) -> 0 | U116: =IFERROR(VLOOKUP(E116,Sheet2!$AA$1:$AB$975,2,FALSE),0) -> 2 | V116: =IFERROR(VLOOKUP(E116,Sheet2!$AC$1:$AD$975,2,FALSE),0) -> 22 | W116: =IFERROR(VLOOKUP(E116,Sheet2!$AE$1:$AF$975,2,FALSE),0) -> 36 | X116: =IFERROR(VLOOKUP(E116,Sheet2!$AG$1:$AH$975,2,FALSE),0) -> 1 | Z116: =IFERROR(VLOOKUP(F116,Sheet2!$AA$1:$AB$975,2,FALSE),0) -> 0 | AA116: =IFERROR(VLOOKUP(F116,Sheet2!$AC$1:$AD$975,2,FALSE),0) -> 0 | AB116: =IFERROR(VLOOKUP(F116,Sheet2!$AE$2:$AF$6539,2,FALSE),0) -> 0 | AC116: =IFERROR(VLOOKUP(F116,Sheet2!$AG$2:$AH$6539,2,FALSE),0) -> 0 | AE116: 0 | AF116: 0 | AG116: 0 | AH116: 0 | AI116: 0 | AJ116: =SUM(AE116+AI116) -> 0 | AK116: =SUM(AJ116*O116) -> 0 | AL116: 0 | AM116: 6
A117: GoBros | B117: 46173 | D117: 048323537933 | E117: WIGF2153_52_bla_1 | F117: ZZWIGF2153_52_bla_1 | G117: #N/A | H117: FBM Only | I117: F2153 | J117: Wigwam Gobi Liner Ultra-Lightweight Crew Socks | K117: Black | L117: Medium | O117: 4.95 | R117: =IFERROR(VLOOKUP(E117,Sheet6!$A$2:$B$500,2,FALSE),0) -> 0 | S117: =IFERROR(VLOOKUP(E117,Sheet6!$C$2:$D$35017,2,FALSE),0) -> 0 | U117: =IFERROR(VLOOKUP(E117,Sheet2!$AA$1:$AB$975,2,FALSE),0) -> 0 | V117: =IFERROR(VLOOKUP(E117,Sheet2!$AC$1:$AD$975,2,FALSE),0) -> 0 | W117: =IFERROR(VLOOKUP(E117,Sheet2!$AE$1:$AF$975,2,FALSE),0) -> 0 | X117: =IFERROR(VLOOKUP(E117,Sheet2!$AG$1:$AH$975,2,FALSE),0) -> 0 | Z117: =IFERROR(VLOOKUP(F117,Sheet2!$AA$1:$AB$975,2,FALSE),0) -> 0 | AA117: =IFERROR(VLOOKUP(F117,Sheet2!$AC$1:$AD$975,2,FALSE),0) -> 0 | AB117: =IFERROR(VLOOKUP(F117,Sheet2!$AE$2:$AF$6539,2,FALSE),0) -> 0 | AC117: =IFERROR(VLOOKUP(F117,Sheet2!$AG$2:$AH$6539,2,FALSE),0) -> 0 | AE117: 0 | AF117: 0 | AG117: 0 | AH117: 0 | AI117: 0 | AJ117: =SUM(AE117+AI117) -> 0 | AK117: =SUM(AJ117*O117) -> 0 | AL117: 0 | AM117: 0
A118: GoBros | B118: 46173 | D118: 048323537940 | E118: WIGF2153_52_bla_2 | F118: ZZWIGF2153_52_bla_2 | G118: #N/A | H118: FBM Only | I118: F2153 | J118: Wigwam Gobi Liner Ultra-Lightweight Crew Socks | K118: Black | L118: Large | O118: 4.95 | R118: =IFERROR(VLOOKUP(E118,Sheet6!$A$2:$B$500,2,FALSE),0) -> 0 | S118: =IFERROR(VLOOKUP(E118,Sheet6!$C$2:$D$35017,2,FALSE),0) -> 0 | U118: =IFERROR(VLOOKUP(E118,Sheet2!$AA$1:$AB$975,2,FALSE),0) -> 6 | V118: =IFERROR(VLOOKUP(E118,Sheet2!$AC$1:$AD$975,2,FALSE),0) -> 66 | W118: =IFERROR(VLOOKUP(E118,Sheet2!$AE$1:$AF$975,2,FALSE),0) -> 27 | X118: =IFERROR(VLOOKUP(E118,Sheet2!$AG$1:$AH$975,2,FALSE),0) -> 1 | Z118: =IFERROR(VLOOKUP(F118,Sheet2!$AA$1:$AB$975,2,FALSE),0) -> 0 | AA118: =IFERROR(VLOOKUP(F118,Sheet2!$AC$1:$AD$975,2,FALSE),0) -> 0 | AB118: =IFERROR(VLOOKUP(F118,Sheet2!$AE$2:$AF$6539,2,FALSE),0) -> 0 | AC118: =IFERROR(VLOOKUP(F118,Sheet2!$AG$2:$AH$6539,2,FALSE),0) -> 0 | AE118: 0 | AF118: 0 | AG118: 0 | AH118: 0 | AI118: 0 | AJ118: =SUM(AE118+AI118) -> 0 | AK118: =SUM(AJ118*O118) -> 0 | AL118: 0 | AM118: 0
A119: GoBros | B119: 46173 | D119: 048323537957 | E119: WIGF2153_52_blk_3 | F119: ZZWIGF2153_52_blk_3 | G119: #N/A | H119: FBM Only | I119: F2153 | J119: Wigwam Gobi Liner Ultra-Lightweight Crew Socks | K119: Black | L119: X-Large | O119: 4.95 | R119: =IFERROR(VLOOKUP(E119,Sheet6!$A$2:$B$500,2,FALSE),0) -> 0 | S119: =IFERROR(VLOOKUP(E119,Sheet6!$C$2:$D$35017,2,FALSE),0) -> 0 | U119: =IFERROR(VLOOKUP(E119,Sheet2!$AA$1:$AB$975,2,FALSE),0) -> 0 | V119: =IFERROR(VLOOKUP(E119,Sheet2!$AC$1:$AD$975,2,FALSE),0) -> 0 | W119: =IFERROR(VLOOKUP(E119,Sheet2!$AE$1:$AF$975,2,FALSE),0) -> 0 | X119: =IFERROR(VLOOKUP(E119,Sheet2!$AG$1:$AH$975,2,FALSE),0) -> 0 | Z119: =IFERROR(VLOOKUP(F119,Sheet2!$AA$1:$AB$975,2,FALSE),0) -> 0 | AA119: =IFERROR(VLOOKUP(F119,Sheet2!$AC$1:$AD$975,2,FALSE),0) -> 0 | AB119: =IFERROR(VLOOKUP(F119,Sheet2!$AE$2:$AF$6539,2,FALSE),0) -> 0 | AC119: =IFERROR(VLOOKUP(F119,Sheet2!$AG$2:$AH$6539,2,FALSE),0) -> 0 | AE119: 0 | AF119: 0 | AG119: 0 | AH119: 0 | AI119: 0 | AJ119: =SUM(AE119+AI119) -> 0 | AK119: =SUM(AJ119*O119) -> 0 | AL119: 0 | AM119: 0
A120: GoBros | B120: 46173 | D120: 048323023320 | E120: WIGF2153_586_nav_1 | F120: ZZWIGF2153_586_nav_1 | G120: #N/A | H120: FBM Only | I120: F2153 | J120: Wigwam Gobi Liner Ultra-Lightweight Crew Socks | K120: Navy | L120: Medium | O120: 4.95 | R120: =IFERROR(VLOOKUP(E120,Sheet6!$A$2:$B$500,2,FALSE),0) -> 0 | S120: =IFERROR(VLOOKUP(E120,Sheet6!$C$2:$D$35017,2,FALSE),0) -> 0 | U120: =IFERROR(VLOOKUP(E120,Sheet2!$AA$1:$AB$975,2,FALSE),0) -> 0 | V120: =IFERROR(VLOOKUP(E120,Sheet2!$AC$1:$AD$975,2,FALSE),0) -> 0 | W120: =IFERROR(VLOOKUP(E120,Sheet2!$AE$1:$AF$975,2,FALSE),0) -> 0 | X120: =IFERROR(VLOOKUP(E120,Sheet2!$AG$1:$AH$975,2,FALSE),0) -> 0 | Z120: =IFERROR(VLOOKUP(F120,Sheet2!$AA$1:$AB$975,2,FALSE),0) -> 0 | AA120: =IFERROR(VLOOKUP(F120,Sheet2!$AC$1:$AD$975,2,FALSE),0) -> 0 | AB120: =IFERROR(VLOOKUP(F120,Sheet2!$AE$2:$AF$6539,2,FALSE),0) -> 0 | AC120: =IFERROR(VLOOKUP(F120,Sheet2!$AG$2:$AH$6539,2,FALSE),0) -> 0 | AE120: 0 | AF120: 0 | AG120: 0 | AH120: 0 | AI120: 0 | AJ120: =SUM(AE120+AI120) -> 0 | AK120: =SUM(AJ120*O120) -> 0 | AL120: 0 | AM120: 12
A121: GoBros | B121: 46173 | D121: 048323023313 | E121: WIGF2153_586_nav_2 | F121: ZZWIGF2153_586_nav_2 | G121: #N/A | H121: FBM Only | I121: F2153 | J121: Wigwam Gobi Liner Ultra-Lightweight Crew Socks | K121: Navy | L121: Large | O121: 4.95 | R121: =IFERROR(VLOOKUP(E121,Sheet6!$A$2:$B$500,2,FALSE),0) -> 0 | S121: =IFERROR(VLOOKUP(E121,Sheet6!$C$2:$D$35017,2,FALSE),0) -> 0 | U121: =IFERROR(VLOOKUP(E121,Sheet2!$AA$1:$AB$975,2,FALSE),0) -> 0 | V121: =IFERROR(VLOOKUP(E121,Sheet2!$AC$1:$AD$975,2,FALSE),0) -> 0 | W121: =IFERROR(VLOOKUP(E121,Sheet2!$AE$1:$AF$975,2,FALSE),0) -> 0 | X121: =IFERROR(VLOOKUP(E121,Sheet2!$AG$1:$AH$975,2,FALSE),0) -> 0 | Z121: =IFERROR(VLOOKUP(F121,Sheet2!$AA$1:$AB$975,2,FALSE),0) -> 0 | AA121: =IFERROR(VLOOKUP(F121,Sheet2!$AC$1:$AD$975,2,FALSE),0) -> 0 | AB121: =IFERROR(VLOOKUP(F121,Sheet2!$AE$2:$AF$6539,2,FALSE),0) -> 0 | AC121: =IFERROR(VLOOKUP(F121,Sheet2!$AG$2:$AH$6539,2,FALSE),0) -> 0 | AE121: 0 | AF121: 0 | AG121: 0 | AH121: 0 | AI121: 0 | AJ121: =SUM(AE121+AI121) -> 0 | AK121: =SUM(AJ121*O121) -> 0 | AL121: 0 | AM121: 0
A122: GoBros | B122: 46173 | D122: 048323023344 | E122: WIGF2153_586_nav_3 | F122: ZZWIGF2153_586_nav_3 | G122: #N/A | H122: FBM Only | I122: F2153 | J122: Wigwam Gobi Liner Ultra-Lightweight Crew Socks | K122: Navy | L122: X-Large | O122: 4.95 | R122: =IFERROR(VLOOKUP(E122,Sheet6!$A$2:$B$500,2,FALSE),0) -> 0 | S122: =IFERROR(VLOOKUP(E122,Sheet6!$C$2:$D$35017,2,FALSE),0) -> 0 | U122: =IFERROR(VLOOKUP(E122,Sheet2!$AA$1:$AB$975,2,FALSE),0) -> 0 | V122: =IFERROR(VLOOKUP(E122,Sheet2!$AC$1:$AD$975,2,FALSE),0) -> 0 | W122: =IFERROR(VLOOKUP(E122,Sheet2!$AE$1:$AF$975,2,FALSE),0) -> 0 | X122: =IFERROR(VLOOKUP(E122,Sheet2!$AG$1:$AH$975,2,FALSE),0) -> 0 | Z122: =IFERROR(VLOOKUP(F122,Sheet2!$AA$1:$AB$975,2,FALSE),0) -> 0 | AA122: =IFERROR(VLOOKUP(F122,Sheet2!$AC$1:$AD$975,2,FALSE),0) -> 0 | AB122: =IFERROR(VLOOKUP(F122,Sheet2!$AE$2:$AF$6539,2,FALSE),0) -> 0 | AC122: =IFERROR(VLOOKUP(F122,Sheet2!$AG$2:$AH$6539,2,FALSE),0) -> 0 | AE122: 0 | AF122: 0 | AG122: 0 | AH122: 0 | AI122: 0 | AJ122: =SUM(AE122+AI122) -> 0 | AK122: =SUM(AJ122*O122) -> 0 | AL122: 0 | AM122: 0
A123: GoBros | B123: 46173 | D123: 048323189101 | E123: WIGF2161_51_whi_0 | F123: ZZWIGF2161_51_whi_0 | G123: #N/A | H123: FBM Only | I123: F2161 | J123: Wigwam Coolmax Liner Ultra-Lightweight Crew Socks | K123: White | L123: Medium/Smalll | O123: 5.4 | R123: =IFERROR(VLOOKUP(E123,Sheet6!$A$2:$B$500,2,FALSE),0) -> 0 | S123: =IFERROR(VLOOKUP(E123,Sheet6!$C$2:$D$35017,2,FALSE),0) -> 0 | U123: =IFERROR(VLOOKUP(E123,Sheet2!$AA$1:$AB$975,2,FALSE),0) -> 0 | V123: =IFERROR(VLOOKUP(E123,Sheet2!$AC$1:$AD$975,2,FALSE),0) -> 0 | W123: =IFERROR(VLOOKUP(E123,Sheet2!$AE$1:$AF$975,2,FALSE),0) -> 0 | X123: =IFERROR(VLOOKUP(E123,Sheet2!$AG$1:$AH$975,2,FALSE),0) -> 0 | Z123: =IFERROR(VLOOKUP(F123,Sheet2!$AA$1:$AB$975,2,FALSE),0) -> 0 | AA123: =IFERROR(VLOOKUP(F123,Sheet2!$AC$1:$AD$975,2,FALSE),0) -> 0 | AB123: =IFERROR(VLOOKUP(F123,Sheet2!$AE$2:$AF$6539,2,FALSE),0) -> 0 | AC123: =IFERROR(VLOOKUP(F123,Sheet2!$AG$2:$AH$6539,2,FALSE),0) -> 0 | AE123: 0 | AF123: 0 | AG123: 0 | AH123: 0 | AI123: 0 | AJ123: =SUM(AE123+AI123) -> 0 | AK123: =SUM(AJ123*O123) -> 0 | AL123: 0 | AM123: 0
A124: GoBros | B124: 46173 | D124: 048323023566 | E124: WIGF2161_51_whi_1 | F124: ZZWIGF2161_51_whi_1 | G124: #N/A | H124: FBM Only | I124: F2161 | J124: Wigwam Coolmax Liner Ultra-Lightweight Crew Socks | K124: White | L124: Medium | O124: 5.4 | R124: =IFERROR(VLOOKUP(E124,Sheet6!$A$2:$B$500,2,FALSE),0) -> 0 | S124: =IFERROR(VLOOKUP(E124,Sheet6!$C$2:$D$35017,2,FALSE),0) -> 0 | U124: =IFERROR(VLOOKUP(E124,Sheet2!$AA$1:$AB$975,2,FALSE),0) -> 10 | V124: =IFERROR(VLOOKUP(E124,Sheet2!$AC$1:$AD$975,2,FALSE),0) -> 120 | W124: =IFERROR(VLOOKUP(E124,Sheet2!$AE$1:$AF$975,2,FALSE),0) -> 9 | X124: =IFERROR(VLOOKUP(E124,Sheet2!$AG$1:$AH$975,2,FALSE),0) -> 0.9 | Z124: =IFERROR(VLOOKUP(F124,Sheet2!$AA$1:$AB$975,2,FALSE),0) -> 0 | AA124: =IFERROR(VLOOKUP(F124,Sheet2!$AC$1:$AD$975,2,FALSE),0) -> 0 | AB124: =IFERROR(VLOOKUP(F124,Sheet2!$AE$2:$AF$6539,2,FALSE),0) -> 0 | AC124: =IFERROR(VLOOKUP(F124,Sheet2!$AG$2:$AH$6539,2,FALSE),0) -> 0 | AE124: 0 | AF124: 0 | AG124: 0 | AH124: 0 | AI124: 0 | AJ124: =SUM(AE124+AI124) -> 0 | AK124: =SUM(AJ124*O124) -> 0 | AL124: 0 | AM124: 30
A125: GoBros | B125: 46173 | D125: 048323023559 | E125: WIGF2161_51_whi_2 | F125: ZZWIGF2161_51_whi_2 | G125: #N/A | H125: FBM Only | I125: F2161 | J125: Wigwam Coolmax Liner Ultra-Lightweight Crew Socks | K125: White | L125: Large | O125: 5.4 | R125: =IFERROR(VLOOKUP(E125,Sheet6!$A$2:$B$500,2,FALSE),0) -> 1 | S125: =IFERROR(VLOOKUP(E125,Sheet6!$C$2:$D$35017,2,FALSE),0) -> 12 | U125: =IFERROR(VLOOKUP(E125,Sheet2!$AA$1:$AB$975,2,FALSE),0) -> 21 | V125: =IFERROR(VLOOKUP(E125,Sheet2!$AC$1:$AD$975,2,FALSE),0) -> 252 | W125: =IFERROR(VLOOKUP(E125,Sheet2!$AE$1:$AF$975,2,FALSE),0) -> 120 | X125: =IFERROR(VLOOKUP(E125,Sheet2!$AG$1:$AH$975,2,FALSE),0) -> 0.9813 | Z125: =IFERROR(VLOOKUP(F125,Sheet2!$AA$1:$AB$975,2,FALSE),0) -> 0 | AA125: =IFERROR(VLOOKUP(F125,Sheet2!$AC$1:$AD$975,2,FALSE),0) -> 0 | AB125: =IFERROR(VLOOKUP(F125,Sheet2!$AE$2:$AF$6539,2,FALSE),0) -> 0 | AC125: =IFERROR(VLOOKUP(F125,Sheet2!$AG$2:$AH$6539,2,FALSE),0) -> 0 | AE125: 1 | AF125: 0 | AG125: 0 | AH125: 0 | AI125: 0 | AJ125: =SUM(AE125+AI125) -> 1 | AK125: =SUM(AJ125*O125) -> 5.4 | AL125: 0 | AM125: 0
A126: GoBros | B126: 46173 | D126: 048323023573 | E126: WIGF2161_51_whi_3 | F126: ZZWIGF2161_51_whi_3 | G126: #N/A | H126: FBM Only | I126: F2161 | J126: Wigwam Coolmax Liner Ultra-Lightweight Crew Socks | K126: White | L126: X-Large | O126: 5.4 | R126: =IFERROR(VLOOKUP(E126,Sheet6!$A$2:$B$500,2,FALSE),0) -> 1 | S126: =IFERROR(VLOOKUP(E126,Sheet6!$C$2:$D$35017,2,FALSE),0) -> 10.2 | U126: =IFERROR(VLOOKUP(E126,Sheet2!$AA$1:$AB$975,2,FALSE),0) -> 15 | V126: =IFERROR(VLOOKUP(E126,Sheet2!$AC$1:$AD$975,2,FALSE),0) -> 180 | W126: =IFERROR(VLOOKUP(E126,Sheet2!$AE$1:$AF$975,2,FALSE),0) -> 43 | X126: =IFERROR(VLOOKUP(E126,Sheet2!$AG$1:$AH$975,2,FALSE),0) -> 0.9688 | Z126: =IFERROR(VLOOKUP(F126,Sheet2!$AA$1:$AB$975,2,FALSE),0) -> 0 | AA126: =IFERROR(VLOOKUP(F126,Sheet2!$AC$1:$AD$975,2,FALSE),0) -> 0 | AB126: =IFERROR(VLOOKUP(F126,Sheet2!$AE$2:$AF$6539,2,FALSE),0) -> 0 | AC126: =IFERROR(VLOOKUP(F126,Sheet2!$AG$2:$AH$6539,2,FALSE),0) -> 0 | AE126: 5 | AF126: 0 | AG126: 0 | AH126: 0 | AI126: 0 | AJ126: =SUM(AE126+AI126) -> 5 | AK126: =SUM(AJ126*O126) -> 27 | AL126: 0 | AM126: 0
... A132: GoBros | B132: 46173 | D132: 048323663441 | E132: WIGF2300_055_gry_0 | F132: ZZWIGF2300_055_gry_0 | G132: #N/A | H132: FBM Only | I132: F2300 | J132: Wigwam Merino Lite Hiker Midweight Crew Socks | K132: Grey Heather | L132: Medium | O132: 9.072 | R132: =IFERROR(VLOOKUP(E132,Sheet6!$A$2:$B$500,2,FALSE),0) -> 0 | S132: =IFERROR(VLOOKUP(E132,Sheet6!$C$2:$D$35017,2,FALSE),0) -> 0 | U132: =IFERROR(VLOOKUP(E132,Sheet2!$AA$1:$AB$975,2,FALSE),0) -> 0 | V132: =IFERROR(VLOOKUP(E132,Sheet2!$AC$1:$AD$975,2,FALSE),0) -> 0 | W132: =IFERROR(VLOOKUP(E132,Sheet2!$AE$1:$AF$975,2,FALSE),0) -> 0 | X132: =IFERROR(VLOOKUP(E132,Sheet2!$AG$1:$AH$975,2,FALSE),0) -> 0 | Z132: =IFERROR(VLOOKUP(F132,Sheet2!$AA$1:$AB$975,2,FALSE),0) -> 1 | AA132: =IFERROR(VLOOKUP(F132,Sheet2!$AC$1:$AD$975,2,FALSE),0) -> 20.99 | AB132: =IFERROR(VLOOKUP(F132,Sheet2!$AE$2:$AF$6539,2,FALSE),0) -> 4 | AC132: =IFERROR(VLOOKUP(F132,Sheet2!$AG$2:$AH$6539,2,FALSE),0) -> 1 | AE132: 12 | AF132: 5 | AG132: 0 | AH132: 0 | AI132: 5 | AJ132: =SUM(AE132+AI132) -> 17 | AK132: =SUM(AJ132*O132) -> 154.224 | AL132: 0 | AM132: 0
A133: GoBros | B133: 46173 | D133: 048323663458 | E133: WIGF2300_055_gry_1 | F133: ZZWIGF2300_055_gry_1 | G133: B07FBJ3K17 | H133: FBM Only | I133: F2300 | J133: Wigwam Merino Lite Hiker Midweight Crew Socks | K133: Grey Heather | L133: Large | O133: 9.072 | R133: =IFERROR(VLOOKUP(E133,Sheet6!$A$2:$B$500,2,FALSE),0) -> 0 | S133: =IFERROR(VLOOKUP(E133,Sheet6!$C$2:$D$35017,2,FALSE),0) -> 0 | U133: =IFERROR(VLOOKUP(E133,Sheet2!$AA$1:$AB$975,2,FALSE),0) -> 0 | V133: =IFERROR(VLOOKUP(E133,Sheet2!$AC$1:$AD$975,2,FALSE),0) -> 0 | W133: =IFERROR(VLOOKUP(E133,Sheet2!$AE$1:$AF$975,2,FALSE),0) -> 0 | X133: =IFERROR(VLOOKUP(E133,Sheet2!$AG$1:$AH$975,2,FALSE),0) -> 0 | Z133: =IFERROR(VLOOKUP(F133,Sheet2!$AA$1:$AB$975,2,FALSE),0) -> 0 | AA133: =IFERROR(VLOOKUP(F133,Sheet2!$AC$1:$AD$975,2,FALSE),0) -> 0 | AB133: =IFERROR(VLOOKUP(F133,Sheet2!$AE$2:$AF$6539,2,FALSE),0) -> 0 | AC133: =IFERROR(VLOOKUP(F133,Sheet2!$AG$2:$AH$6539,2,FALSE),0) -> 0 | AE133: 2 | AF133: 10 | AG133: 0 | AH133: 0 | AI133: 10 | AJ133: =SUM(AE133+AI133) -> 12 | AK133: =SUM(AJ133*O133) -> 108.864 | AL133: 0 | AM133: 0
A134: GoBros | B134: 46173 | D134: 048323629683 | E134: WIGF2300_18F_nav_1 | F134: ZZWIGF2300_18F_nav_1 | G134: #N/A | H134: FBM Only | I134: F2300 | J134: Wigwam Merino Lite Hiker Midweight Crew Socks | K134: Navy I | L134: Medium | O134: 9.072 | R134: =IFERROR(VLOOKUP(E134,Sheet6!$A$2:$B$500,2,FALSE),0) -> 0 | S134: =IFERROR(VLOOKUP(E134,Sheet6!$C$2:$D$35017,2,FALSE),0) -> 0 | U134: =IFERROR(VLOOKUP(E134,Sheet2!$AA$1:$AB$975,2,FALSE),0) -> 0 | V134: =IFERROR(VLOOKUP(E134,Sheet2!$AC$1:$AD$975,2,FALSE),0) -> 0 | W134: =IFERROR(VLOOKUP(E134,Sheet2!$AE$1:$AF$975,2,FALSE),0) -> 0 | X134: =IFERROR(VLOOKUP(E134,Sheet2!$AG$1:$AH$975,2,FALSE),0) -> 0 | Z134: =IFERROR(VLOOKUP(F134,Sheet2!$AA$1:$AB$975,2,FALSE),0) -> 0 | AA134: =IFERROR(VLOOKUP(F134,Sheet2!$AC$1:$AD$975,2,FALSE),0) -> 0 | AB134: =IFERROR(VLOOKUP(F134,Sheet2!$AE$2:$AF$6539,2,FALSE),0) -> 0 | AC134: =IFERROR(VLOOKUP(F134,Sheet2!$AG$2:$AH$6539,2,FALSE),0) -> 0 | AE134: 12 | AF134: 0 | AG134: 0 | AH134: 0 | AI134: 0 | AJ134: =SUM(AE134+AI134) -> 12 | AK134: =SUM(AJ134*O134) -> 108.864 | AL134: 0 | AM134: 0
A135: GoBros | B135: 46173 | D135: 048323629690 | E135: WIGF2300_18F_nav_2 | F135: ZZWIGF2300_18F_nav_2 | G135: #N/A | H135: FBM Only | I135: F2300 | J135: Wigwam Merino Lite Hiker Midweight Crew Socks | K135: Navy I | L135: Large | O135: 9.072 | R135: =IFERROR(VLOOKUP(E135,Sheet6!$A$2:$B$500,2,FALSE),0) -> 0 | S135: =IFERROR(VLOOKUP(E135,Sheet6!$C$2:$D$35017,2,FALSE),0) -> 0 | U135: =IFERROR(VLOOKUP(E135,Sheet2!$AA$1:$AB$975,2,FALSE),0) -> 0 | V135: =IFERROR(VLOOKUP(E135,Sheet2!$AC$1:$AD$975,2,FALSE),0) -> 0 | W135: =IFERROR(VLOOKUP(E135,Sheet2!$AE$1:$AF$975,2,FALSE),0) -> 0 | X135: =IFERROR(VLOOKUP(E135,Sheet2!$AG$1:$AH$975,2,FALSE),0) -> 0 | Z135: =IFERROR(VLOOKUP(F135,Sheet2!$AA$1:$AB$975,2,FALSE),0) -> 4 | AA135: =IFERROR(VLOOKUP(F135,Sheet2!$AC$1:$AD$975,2,FALSE),0) -> 83.96 | AB135: =IFERROR(VLOOKUP(F135,Sheet2!$AE$2:$AF$6539,2,FALSE),0) -> 31 | AC135: =IFERROR(VLOOKUP(F135,Sheet2!$AG$2:$AH$6539,2,FALSE),0) -> 1 | AE135: 10 | AF135: 18 | AG135: 0 | AH135: 0 | AI135: 18 | AJ135: =SUM(AE135+AI135) -> 28 | AK135: =SUM(AJ135*O135) -> 254.016 | AL135: 0 | AM135: 0
A136: GoBros | B136: 46173 | D136: 048323630160 | E136: WIGF2300_86D_oxf_1 | F136: ZZWIGF2300_86D_oxf_1 | G136: #N/A | H136: FBM Only | I136: F2300 | J136: Wigwam Merino Lite Hiker Midweight Crew Socks | K136: Oxford | L136: Medium | O136: 9.072 | R136: =IFERROR(VLOOKUP(E136,Sheet6!$A$2:$B$500,2,FALSE),0) -> 0 | S136: =IFERROR(VLOOKUP(E136,Sheet6!$C$2:$D$35017,2,FALSE),0) -> 0 | U136: =IFERROR(VLOOKUP(E136,Sheet2!$AA$1:$AB$975,2,FALSE),0) -> 0 | V136: =IFERROR(VLOOKUP(E136,Sheet2!$AC$1:$AD$975,2,FALSE),0) -> 0 | W136: =IFERROR(VLOOKUP(E136,Sheet2!$AE$1:$AF$975,2,FALSE),0) -> 0 | X136: =IFERROR(VLOOKUP(E136,Sheet2!$AG$1:$AH$975,2,FALSE),0) -> 0 | Z136: =IFERROR(VLOOKUP(F136,Sheet2!$AA$1:$AB$975,2,FALSE),0) -> 4 | AA136: =IFERROR(VLOOKUP(F136,Sheet2!$AC$1:$AD$975,2,FALSE),0) -> 83.96 | AB136: =IFERROR(VLOOKUP(F136,Sheet2!$AE$2:$AF$6539,2,FALSE),0) -> 57 | AC136: =IFERROR(VLOOKUP(F136,Sheet2!$AG$2:$AH$6539,2,FALSE),0) -> 0.6667 | AE136: 11 | AF136: 8 | AG136: 0 | AH136: 0 | AI136: 8 | AJ136: =SUM(AE136+AI136) -> 19 | AK136: =SUM(AJ136*O136) -> 172.368 | AL136: 0 | AM136: 0
A137: GoBros | B137: 46173 | D137: 048323630177 | E137: WIGF2300_86D_oxf_2 | F137: ZZWIGF2300_86D_oxf_2 | G137: #N/A | H137: FBA | I137: F2300 | J137: Wigwam Merino Lite Hiker Midweight Crew Socks | K137: Oxford | L137: Large | O137: 9.072 | R137: =IFERROR(VLOOKUP(E137,Sheet6!$A$2:$B$500,2,FALSE),0) -> 3 | S137: =IFERROR(VLOOKUP(E137,Sheet6!$C$2:$D$35017,2,FALSE),0) -> 63 | U137: =IFERROR(VLOOKUP(E137,Sheet2!$AA$1:$AB$975,2,FALSE),0) -> 0 | V137: =IFERROR(VLOOKUP(E137,Sheet2!$AC$1:$AD$975,2,FALSE),0) -> 0 | W137: =IFERROR(VLOOKUP(E137,Sheet2!$AE$1:$AF$975,2,FALSE),0) -> 0 | X137: =IFERROR(VLOOKUP(E137,Sheet2!$AG$1:$AH$975,2,FALSE),0) -> 0 | Z137: =IFERROR(VLOOKUP(F137,Sheet2!$AA$1:$AB$975,2,FALSE),0) -> 17 | AA137: =IFERROR(VLOOKUP(F137,Sheet2!$AC$1:$AD$975,2,FALSE),0) -> 356.83 | AB137: =IFERROR(VLOOKUP(F137,Sheet2!$AE$2:$AF$6539,2,FALSE),0) -> 46 | AC137: =IFERROR(VLOOKUP(F137,Sheet2!$AG$2:$AH$6539,2,FALSE),0) -> 0.9828 | AE137: 26 | AF137: 51 | AG137: 0 | AH137: 1 | AI137: 52 | AJ137: =SUM(AE137+AI137) -> 78 | AK137: =SUM(AJ137*O137) -> 707.616 | AL137: 0 | AM137: 30
A138: GoBros | B138: 46173 | D138: 048323630184 | E138: WIGF2300_86D_oxf_3 | F138: ZZWIGF2300_86D_oxf_3 | G138: #N/A | H138: FBA | I138: F2300 | J138: Wigwam Merino Lite Hiker Midweight Crew Socks | K138: Oxford | L138: X-Large | O138: 9.072 | R138: =IFERROR(VLOOKUP(E138,Sheet6!$A$2:$B$500,2,FALSE),0) -> 0 | S138: =IFERROR(VLOOKUP(E138,Sheet6!$C$2:$D$35017,2,FALSE),0) -> 0 | U138: =IFERROR(VLOOKUP(E138,Sheet2!$AA$1:$AB$975,2,FALSE),0) -> 0 | V138: =IFERROR(VLOOKUP(E138,Sheet2!$AC$1:$AD$975,2,FALSE),0) -> 0 | W138: =IFERROR(VLOOKUP(E138,Sheet2!$AE$1:$AF$975,2,FALSE),0) -> 0 | X138: =IFERROR(VLOOKUP(E138,Sheet2!$AG$1:$AH$975,2,FALSE),0) -> 0 | Z138: =IFERROR(VLOOKUP(F138,Sheet2!$AA$1:$AB$975,2,FALSE),0) -> 7 | AA138: =IFERROR(VLOOKUP(F138,Sheet2!$AC$1:$AD$975,2,FALSE),0) -> 146.93 | AB138: =IFERROR(VLOOKUP(F138,Sheet2!$AE$2:$AF$6539,2,FALSE),0) -> 39 | AC138: =IFERROR(VLOOKUP(F138,Sheet2!$AG$2:$AH$6539,2,FALSE),0) -> 0.9773 | AE138: 18 | AF138: 29 | AG138: 0 | AH138: 2 | AI138: 31 | AJ138: =SUM(AE138+AI138) -> 49 | AK138: =SUM(AJ138*O138) -> 444.528 | AL138: 6 | AM138: 0
A139: GoBros | B139: 46173 | D139: 048323623797 | E139: WIGF2322_22F_blk_0 | F139: ZZWIGF2322_22F_blk_0 | G139: #N/A | H139: FBA | I139: F2322 | J139: Wigwam Merino Comfort Hiker Midweight Crew Socks | K139: Black II | L139: Medium | O139: 8.64 | R139: =IFERROR(VLOOKUP(E139,Sheet6!$A$2:$B$500,2,FALSE),0) -> 0 | S139: =IFERROR(VLOOKUP(E139,Sheet6!$C$2:$D$35017,2,FALSE),0) -> 0 | U139: =IFERROR(VLOOKUP(E139,Sheet2!$AA$1:$AB$975,2,FALSE),0) -> 2 | V139: =IFERROR(VLOOKUP(E139,Sheet2!$AC$1:$AD$975,2,FALSE),0) -> 39.98 | W139: =IFERROR(VLOOKUP(E139,Sheet2!$AE$1:$AF$975,2,FALSE),0) -> 110 | X139: =IFERROR(VLOOKUP(E139,Sheet2!$AG$1:$AH$975,2,FALSE),0) -> 0.8296 | Z139: =IFERROR(VLOOKUP(F139,Sheet2!$AA$1:$AB$975,2,FALSE),0) -> 11 | AA139: =IFERROR(VLOOKUP(F139,Sheet2!$AC$1:$AD$975,2,FALSE),0) -> 219.89 | AB139: =IFERROR(VLOOKUP(F139,Sheet2!$AE$2:$AF$6539,2,FALSE),0) -> 110 | AC139: =IFERROR(VLOOKUP(F139,Sheet2!$AG$2:$AH$6539,2,FALSE),0) -> 0.8296 | AE139: 27 | AF139: 19 | AG139: 0 | AH139: 0 | AI139: 19 | AJ139: =SUM(AE139+AI139) -> 46 | AK139: =SUM(AJ139*O139) -> 397.44 | AL139: 12 | AM139: 0
A140: GoBros | B140: 46173 | D140: 048323623803 | E140: WIGF2322_22F_blk_1 | F140: ZZWIGF2322_22F_blk_1 | G140: #N/A | H140: FBA | I140: F2322 | J140: Wigwam Merino Comfort Hiker Midweight Crew Socks | K140: Black II | L140: Large | O140: 8.64 | R140: =IFERROR(VLOOKUP(E140,Sheet6!$A$2:$B$500,2,FALSE),0) -> 1 | S140: =IFERROR(VLOOKUP(E140,Sheet6!$C$2:$D$35017,2,FALSE),0) -> 20 | U140: =IFERROR(VLOOKUP(E140,Sheet2!$AA$1:$AB$975,2,FALSE),0) -> 0 | V140: =IFERROR(VLOOKUP(E140,Sheet2!$AC$1:$AD$975,2,FALSE),0) -> 0 | W140: =IFERROR(VLOOKUP(E140,Sheet2!$AE$1:$AF$975,2,FALSE),0) -> 0 | X140: =IFERROR(VLOOKUP(E140,Sheet2!$AG$1:$AH$975,2,FALSE),0) -> 0 | Z140: =IFERROR(VLOOKUP(F140,Sheet2!$AA$1:$AB$975,2,FALSE),0) -> 13 | AA140: =IFERROR(VLOOKUP(F140,Sheet2!$AC$1:$AD$975,2,FALSE),0) -> 259.87 | AB140: =IFERROR(VLOOKUP(F140,Sheet2!$AE$2:$AF$6539,2,FALSE),0) -> 207 | AC140: =IFERROR(VLOOKUP(F140,Sheet2!$AG$2:$AH$6539,2,FALSE),0) -> 0.3386 | AE140: 47 | AF140: 0 | AG140: 0 | AH140: 12 | AI140: 12 | AJ140: =SUM(AE140+AI140) -> 59 | AK140: =SUM(AJ140*O140) -> 509.76 | AL140: 60 | AM140: 12
A141: GoBros | B141: 46173 | D141: 048323623810 | E141: WIGF2322_22F_blk_2 | F141: ZZWIGF2322_22F_blk_2 | G141: #N/A | H141: FBA | I141: F2322 | J141: Wigwam Merino Comfort Hiker Midweight Crew Socks | K141: Black II | L141: X-Large | O141: 8.64 | R141: =IFERROR(VLOOKUP(E141,Sheet6!$A$2:$B$500,2,FALSE),0) -> 0 | S141: =IFERROR(VLOOKUP(E141,Sheet6!$C$2:$D$35017,2,FALSE),0) -> 0 | U141: =IFERROR(VLOOKUP(E141,Sheet2!$AA$1:$AB$975,2,FALSE),0) -> 0 | V141: =IFERROR(VLOOKUP(E141,Sheet2!$AC$1:$AD$975,2,FALSE),0) -> 0 | W141: =IFERROR(VLOOKUP(E141,Sheet2!$AE$1:$AF$975,2,FALSE),0) -> 0 | X141: =IFERROR(VLOOKUP(E141,Sheet2!$AG$1:$AH$975,2,FALSE),0) -> 0 | Z141: =IFERROR(VLOOKUP(F141,Sheet2!$AA$1:$AB$975,2,FALSE),0) -> 16 | AA141: =IFERROR(VLOOKUP(F141,Sheet2!$AC$1:$AD$975,2,FALSE),0) -> 319.84 | AB141: =IFERROR(VLOOKUP(F141,Sheet2!$AE$2:$AF$6539,2,FALSE),0) -> 139 | AC141: =IFERROR(VLOOKUP(F141,Sheet2!$AG$2:$AH$6539,2,FALSE),0) -> 0.5722 | AE141: 148 | AF141: 12 | AG141: 0 | AH141: 0 | AI141: 12 | AJ141: =SUM(AE141+AI141) -> 160 | AK141: =SUM(AJ141*O141) -> 1382.4 | AL141: 12 | AM141: 60
A142: GoBros | B142: 46173 | D142: 048323623858 | E142: WIGF2322_360_pur_0 | F142: ZZWIGF2322_360_pur_0 | G142: #N/A | H142: FBA | I142: F2322 | J142: Wigwam Merino Comfort Hiker Midweight Crew Socks | K142: Purple Velvet | L142: Medium | O142: 8.64 | R142: =IFERROR(VLOOKUP(E142,Sheet6!$A$2:$B$500,2,FALSE),0) -> 0 | S142: =IFERROR(VLOOKUP(E142,Sheet6!$C$2:$D$35017,2,FALSE),0) -> 0 | U142: =IFERROR(VLOOKUP(E142,Sheet2!$AA$1:$AB$975,2,FALSE),0) -> 0 | V142: =IFERROR(VLOOKUP(E142,Sheet2!$AC$1:$AD$975,2,FALSE),0) -> 0 | W142: =IFERROR(VLOOKUP(E142,Sheet2!$AE$1:$AF$975,2,FALSE),0) -> 0 | X142: =IFERROR(VLOOKUP(E142,Sheet2!$AG$1:$AH$975,2,FALSE),0) -> 0 | Z142: =IFERROR(VLOOKUP(F142,Sheet2!$AA$1:$AB$975,2,FALSE),0) -> 0 | AA142: =IFERROR(VLOOKUP(F142,Sheet2!$AC$1:$AD$975,2,FALSE),0) -> 0 | AB142: =IFERROR(VLOOKUP(F142,Sheet2!$AE$2:$AF$6539,2,FALSE),0) -> 0 | AC142: =IFERROR(VLOOKUP(F142,Sheet2!$AG$2:$AH$6539,2,FALSE),0) -> 0 | AE142: 0 | AF142: 0 | AG142: 0 | AH142: 0 | AI142: 0 | AJ142: =SUM(AE142+AI142) -> 0 | AK142: =SUM(AJ142*O142) -> 0 | AL142: 18 | AM142: 39
A143: GoBros | B143: 46173 | D143: 048323623971 | E143: WIGF2322_586_nvy_0 | F143: ZZWIGF2322_586_nvy_0 | G143: #N/A | H143: FBA | I143: F2322 | J143: Wigwam Merino Comfort Hiker Midweight Crew Socks | K143: Navy II | L143: Medium | O143: 8.64 | R143: =IFERROR(VLOOKUP(E143,Sheet6!$A$2:$B$500,2,FALSE),0) -> 0 | S143: =IFERROR(VLOOKUP(E143,Sheet6!$C$2:$D$35017,2,FALSE),0) -> 0 | U143: =IFERROR(VLOOKUP(E143,Sheet2!$AA$1:$AB$975,2,FALSE),0) -> 0 | V143: =IFERROR(VLOOKUP(E143,Sheet2!$AC$1:$AD$975,2,FALSE),0) -> 0 | W143: =IFERROR(VLOOKUP(E143,Sheet2!$AE$1:$AF$975,2,FALSE),0) -> 0 | X143: =IFERROR(VLOOKUP(E143,Sheet2!$AG$1:$AH$975,2,FALSE),0) -> 0 | Z143: =IFERROR(VLOOKUP(F143,Sheet2!$AA$1:$AB$975,2,FALSE),0) -> 0 | AA143: =IFERROR(VLOOKUP(F143,Sheet2!$AC$1:$AD$975,2,FALSE),0) -> 0 | AB143: =IFERROR(VLOOKUP(F143,Sheet2!$AE$2:$AF$6539,2,FALSE),0) -> 0 | AC143: =IFERROR(VLOOKUP(F143,Sheet2!$AG$2:$AH$6539,2,FALSE),0) -> 0 | AE143: 40 | AF143: 0 | AG143: 0 | AH143: 0 | AI143: 0 | AJ143: =SUM(AE143+AI143) -> 40 | AK143: =SUM(AJ143*O143) -> 345.6 | AL143: 12 | AM143: 0
A144: GoBros | B144: 46173 | D144: 048323623988 | E144: WIGF2322_586_nvy_1 | F144: ZZWIGF2322_586_nvy_1 | G144: #N/A | H144: FBA | I144: F2322 | J144: Wigwam Merino Comfort Hiker Midweight Crew Socks | K144: Navy II | L144: Large | O144: 8.64 | R144: =IFERROR(VLOOKUP(E144,Sheet6!$A$2:$B$500,2,FALSE),0) -> 0 | S144: =IFERROR(VLOOKUP(E144,Sheet6!$C$2:$D$35017,2,FALSE),0) -> 0 | U144: =IFERROR(VLOOKUP(E144,Sheet2!$AA$1:$AB$975,2,FALSE),0) -> 0 | V144: =IFERROR(VLOOKUP(E144,Sheet2!$AC$1:$AD$975,2,FALSE),0) -> 0 | W144: =IFERROR(VLOOKUP(E144,Sheet2!$AE$1:$AF$975,2,FALSE),0) -> 0 | X144: =IFERROR(VLOOKUP(E144,Sheet2!$AG$1:$AH$975,2,FALSE),0) -> 0 | Z144: =IFERROR(VLOOKUP(F144,Sheet2!$AA$1:$AB$975,2,FALSE),0) -> 11 | AA144: =IFERROR(VLOOKUP(F144,Sheet2!$AC$1:$AD$975,2,FALSE),0) -> 219.89 | AB144: =IFERROR(VLOOKUP(F144,Sheet2!$AE$2:$AF$6539,2,FALSE),0) -> 116 | AC144: =IFERROR(VLOOKUP(F144,Sheet2!$AG$2:$AH$6539,2,FALSE),0) -> 0.626 | AE144: 95 | AF144: 27 | AG144: 0 | AH144: 18 | AI144: 45 | AJ144: =SUM(AE144+AI144) -> 140 | AK144: =SUM(AJ144*O144) -> 1209.6 | AL144: 30 | AM144: 0
A145: GoBros | B145: 46173 | D145: 048323623995 | E145: WIGF2322_586_nvy_2 | F145: ZZWIGF2322_586_nvy_2 | G145: #N/A | H145: FBA | I145: F2322 | J145: Wigwam Merino Comfort Hiker Midweight Crew Socks | K145: Navy II | L145: X-Large | O145: 8.64 | R145: =IFERROR(VLOOKUP(E145,Sheet6!$A$2:$B$500,2,FALSE),0) -> 0 | S145: =IFERROR(VLOOKUP(E145,Sheet6!$C$2:$D$35017,2,FALSE),0) -> 0 | U145: =IFERROR(VLOOKUP(E145,Sheet2!$AA$1:$AB$975,2,FALSE),0) -> 0 | V145: =IFERROR(VLOOKUP(E145,Sheet2!$AC$1:$AD$975,2,FALSE),0) -> 0 | W145: =IFERROR(VLOOKUP(E145,Sheet2!$AE$1:$AF$975,2,FALSE),0) -> 0 | X145: =IFERROR(VLOOKUP(E145,Sheet2!$AG$1:$AH$975,2,FALSE),0) -> 0 | Z145: =IFERROR(VLOOKUP(F145,Sheet2!$AA$1:$AB$975,2,FALSE),0) -> 12 | AA145: =IFERROR(VLOOKUP(F145,Sheet2!$AC$1:$AD$975,2,FALSE),0) -> 239.88 | AB145: =IFERROR(VLOOKUP(F145,Sheet2!$AE$2:$AF$6539,2,FALSE),0) -> 90 | AC145: =IFERROR(VLOOKUP(F145,Sheet2!$AG$2:$AH$6539,2,FALSE),0) -> 0.7524 | AE145: 29 | AF145: 8 | AG145: 0 | AH145: 0 | AI145: 8 | AJ145: =SUM(AE145+AI145) -> 37 | AK145: =SUM(AJ145*O145) -> 319.68 | AL145: 6 | AM145: 0
... A163: GoBros | B163: 46173 | D163: 048323609463 | E163: WIGF2432_052_bla_2 | F163: ZZWIGF2432_052_bla_2 | G163: #N/A | H163: FBM Only | I163: F2432 | J163: Wigwam Merino Woodland Boot Socks | K163: Black | L163: Large | O163: 9.495 | R163: =IFERROR(VLOOKUP(E163,Sheet6!$A$2:$B$500,2,FALSE),0) -> 0 | S163: =IFERROR(VLOOKUP(E163,Sheet6!$C$2:$D$35017,2,FALSE),0) -> 0 | U163: =IFERROR(VLOOKUP(E163,Sheet2!$AA$1:$AB$975,2,FALSE),0) -> 0 | V163: =IFERROR(VLOOKUP(E163,Sheet2!$AC$1:$AD$975,2,FALSE),0) -> 0 | W163: =IFERROR(VLOOKUP(E163,Sheet2!$AE$1:$AF$975,2,FALSE),0) -> 0 | X163: =IFERROR(VLOOKUP(E163,Sheet2!$AG$1:$AH$975,2,FALSE),0) -> 0 | Z163: =IFERROR(VLOOKUP(F163,Sheet2!$AA$1:$AB$975,2,FALSE),0) -> 0 | AA163: =IFERROR(VLOOKUP(F163,Sheet2!$AC$1:$AD$975,2,FALSE),0) -> 0 | AB163: =IFERROR(VLOOKUP(F163,Sheet2!$AE$2:$AF$6539,2,FALSE),0) -> 0 | AC163: =IFERROR(VLOOKUP(F163,Sheet2!$AG$2:$AH$6539,2,FALSE),0) -> 0 | AE163: 25 | AF163: 0 | AG163: 0 | AH163: 0 | AI163: 0 | AJ163: =SUM(AE163+AI163) -> 25 | AK163: =SUM(AJ163*O163) -> 237.375 | AL163: 0 | AM163: 0
A164: GoBros | B164: 46173 | D164: 048323609470 | E164: WIGF2432_052_bla_3 | F164: ZZWIGF2432_052_bla_3 | G164: B07MFWFSC6 | H164: FBM Only | I164: F2432 | J164: Wigwam Merino Woodland Boot Socks | K164: Black | L164: X-Large | O164: 9.495 | R164: =IFERROR(VLOOKUP(E164,Sheet6!$A$2:$B$500,2,FALSE),0) -> 0 | S164: =IFERROR(VLOOKUP(E164,Sheet6!$C$2:$D$35017,2,FALSE),0) -> 0 | U164: =IFERROR(VLOOKUP(E164,Sheet2!$AA$1:$AB$975,2,FALSE),0) -> 0 | V164: =IFERROR(VLOOKUP(E164,Sheet2!$AC$1:$AD$975,2,FALSE),0) -> 0 | W164: =IFERROR(VLOOKUP(E164,Sheet2!$AE$1:$AF$975,2,FALSE),0) -> 0 | X164: =IFERROR(VLOOKUP(E164,Sheet2!$AG$1:$AH$975,2,FALSE),0) -> 0 | Z164: =IFERROR(VLOOKUP(F164,Sheet2!$AA$1:$AB$975,2,FALSE),0) -> 0 | AA164: =IFERROR(VLOOKUP(F164,Sheet2!$AC$1:$AD$975,2,FALSE),0) -> 0 | AB164: =IFERROR(VLOOKUP(F164,Sheet2!$AE$2:$AF$6539,2,FALSE),0) -> 0 | AC164: =IFERROR(VLOOKUP(F164,Sheet2!$AG$2:$AH$6539,2,FALSE),0) -> 0 | AE164: 9 | AF164: 0 | AG164: 0 | AH164: 0 | AI164: 0 | AJ164: =SUM(AE164+AI164) -> 9 | AK164: =SUM(AJ164*O164) -> 85.455 | AL164: 0 | AM164: 0
A165: GoBros | B165: 46173 | D165: 048323609487 | E165: WIGF2432_057_cha_1 | F165: ZZWIGF2432_057_cha_1 | G165: #N/A | H165: FBM Only | I165: F2432 | J165: Wigwam Merino Woodland Boot Socks | K165: Charcoal | L165: Medium | O165: 9.495 | R165: =IFERROR(VLOOKUP(E165,Sheet6!$A$2:$B$500,2,FALSE),0) -> 0 | S165: =IFERROR(VLOOKUP(E165,Sheet6!$C$2:$D$35017,2,FALSE),0) -> 0 | U165: =IFERROR(VLOOKUP(E165,Sheet2!$AA$1:$AB$975,2,FALSE),0) -> 0 | V165: =IFERROR(VLOOKUP(E165,Sheet2!$AC$1:$AD$975,2,FALSE),0) -> 0 | W165: =IFERROR(VLOOKUP(E165,Sheet2!$AE$1:$AF$975,2,FALSE),0) -> 0 | X165: =IFERROR(VLOOKUP(E165,Sheet2!$AG$1:$AH$975,2,FALSE),0) -> 0 | Z165: =IFERROR(VLOOKUP(F165,Sheet2!$AA$1:$AB$975,2,FALSE),0) -> 0 | AA165: =IFERROR(VLOOKUP(F165,Sheet2!$AC$1:$AD$975,2,FALSE),0) -> 0 | AB165: =IFERROR(VLOOKUP(F165,Sheet2!$AE$2:$AF$6539,2,FALSE),0) -> 0 | AC165: =IFERROR(VLOOKUP(F165,Sheet2!$AG$2:$AH$6539,2,FALSE),0) -> 0 | AE165: 0 | AF165: 0 | AG165: 0 | AH165: 0 | AI165: 0 | AJ165: =SUM(AE165+AI165) -> 0 | AK165: =SUM(AJ165*O165) -> 0 | AL165: 0 | AM165: 0
A166: GoBros | B166: 46173 | D166: 048323609494 | E166: WIGF2432_057_cha_2 | F166: ZZWIGF2432_057_cha_2 | G166: #N/A | H166: FBM Only | I166: F2432 | J166: Wigwam Merino Woodland Boot Socks | K166: Charcoal | L166: Large | O166: 9.495 | R166: =IFERROR(VLOOKUP(E166,Sheet6!$A$2:$B$500,2,FALSE),0) -> 0 | S166: =IFERROR(VLOOKUP(E166,Sheet6!$C$2:$D$35017,2,FALSE),0) -> 0 | U166: =IFERROR(VLOOKUP(E166,Sheet2!$AA$1:$AB$975,2,FALSE),0) -> 0 | V166: =IFERROR(VLOOKUP(E166,Sheet2!$AC$1:$AD$975,2,FALSE),0) -> 0 | W166: =IFERROR(VLOOKUP(E166,Sheet2!$AE$1:$AF$975,2,FALSE),0) -> 0 | X166: =IFERROR(VLOOKUP(E166,Sheet2!$AG$1:$AH$975,2,FALSE),0) -> 0 | Z166: =IFERROR(VLOOKUP(F166,Sheet2!$AA$1:$AB$975,2,FALSE),0) -> 0 | AA166: =IFERROR(VLOOKUP(F166,Sheet2!$AC$1:$AD$975,2,FALSE),0) -> 0 | AB166: =IFERROR(VLOOKUP(F166,Sheet2!$AE$2:$AF$6539,2,FALSE),0) -> 0 | AC166: =IFERROR(VLOOKUP(F166,Sheet2!$AG$2:$AH$6539,2,FALSE),0) -> 0 | AE166: 0 | AF166: 0 | AG166: 0 | AH166: 0 | AI166: 0 | AJ166: =SUM(AE166+AI166) -> 0 | AK166: =SUM(AJ166*O166) -> 0 | AL166: 0 | AM166: 0
A167: GoBros | B167: 46173 | D167: 048323609500 | E167: WIGF2432_057_cha_3 | F167: ZZWIGF2432_057_cha_3 | G167: #N/A | H167: FBM Only | I167: F2432 | J167: Wigwam Merino Woodland Boot Socks | K167: Charcoal | L167: X-Large | O167: 9.495 | R167: =IFERROR(VLOOKUP(E167,Sheet6!$A$2:$B$500,2,FALSE),0) -> 0 | S167: =IFERROR(VLOOKUP(E167,Sheet6!$C$2:$D$35017,2,FALSE),0) -> 0 | U167: =IFERROR(VLOOKUP(E167,Sheet2!$AA$1:$AB$975,2,FALSE),0) -> 0 | V167: =IFERROR(VLOOKUP(E167,Sheet2!$AC$1:$AD$975,2,FALSE),0) -> 0 | W167: =IFERROR(VLOOKUP(E167,Sheet2!$AE$1:$AF$975,2,FALSE),0) -> 0 | X167: =IFERROR(VLOOKUP(E167,Sheet2!$AG$1:$AH$975,2,FALSE),0) -> 0 | Z167: =IFERROR(VLOOKUP(F167,Sheet2!$AA$1:$AB$975,2,FALSE),0) -> 0 | AA167: =IFERROR(VLOOKUP(F167,Sheet2!$AC$1:$AD$975,2,FALSE),0) -> 0 | AB167: =IFERROR(VLOOKUP(F167,Sheet2!$AE$2:$AF$6539,2,FALSE),0) -> 0 | AC167: =IFERROR(VLOOKUP(F167,Sheet2!$AG$2:$AH$6539,2,FALSE),0) -> 0 | AE167: 0 | AF167: 0 | AG167: 0 | AH167: 0 | AI167: 0 | AJ167: =SUM(AE167+AI167) -> 0 | AK167: =SUM(AJ167*O167) -> 0 | AL167: 0 | AM167: 0
A168: GoBros | B168: 46173 | D168: 048323609548 | E168: WIGF2432_125_lod_1 | F168: ZZWIGF2432_125_lod_1 | G168: #N/A | H168: FBA | I168: F2432 | J168: Wigwam Merino Woodland Boot Socks | K168: Loden | L168: Medium | O168: 9.495 | R168: =IFERROR(VLOOKUP(E168,Sheet6!$A$2:$B$500,2,FALSE),0) -> 0 | S168: =IFERROR(VLOOKUP(E168,Sheet6!$C$2:$D$35017,2,FALSE),0) -> 0 | U168: =IFERROR(VLOOKUP(E168,Sheet2!$AA$1:$AB$975,2,FALSE),0) -> 0 | V168: =IFERROR(VLOOKUP(E168,Sheet2!$AC$1:$AD$975,2,FALSE),0) -> 0 | W168: =IFERROR(VLOOKUP(E168,Sheet2!$AE$1:$AF$975,2,FALSE),0) -> 0 | X168: =IFERROR(VLOOKUP(E168,Sheet2!$AG$1:$AH$975,2,FALSE),0) -> 0 | Z168: =IFERROR(VLOOKUP(F168,Sheet2!$AA$1:$AB$975,2,FALSE),0) -> 0 | AA168: =IFERROR(VLOOKUP(F168,Sheet2!$AC$1:$AD$975,2,FALSE),0) -> 0 | AB168: =IFERROR(VLOOKUP(F168,Sheet2!$AE$2:$AF$6539,2,FALSE),0) -> 0 | AC168: =IFERROR(VLOOKUP(F168,Sheet2!$AG$2:$AH$6539,2,FALSE),0) -> 0 | AE168: 0 | AF168: 0 | AG168: 0 | AH168: 0 | AI168: 0 | AJ168: =SUM(AE168+AI168) -> 0 | AK168: =SUM(AJ168*O168) -> 0 | AL168: 0 | AM168: 0
A169: GoBros | B169: 46173 | D169: 048323609555 | E169: WIGF2432_125_lod_2 | F169: ZZWIGF2432_125_lod_2 | G169: #N/A | H169: FBA | I169: F2432 | J169: Wigwam Merino Woodland Boot Socks | K169: Loden | L169: Large | O169: 9.495 | R169: =IFERROR(VLOOKUP(E169,Sheet6!$A$2:$B$500,2,FALSE),0) -> 0 | S169: =IFERROR(VLOOKUP(E169,Sheet6!$C$2:$D$35017,2,FALSE),0) -> 0 | U169: =IFERROR(VLOOKUP(E169,Sheet2!$AA$1:$AB$975,2,FALSE),0) -> 0 | V169: =IFERROR(VLOOKUP(E169,Sheet2!$AC$1:$AD$975,2,FALSE),0) -> 0 | W169: =IFERROR(VLOOKUP(E169,Sheet2!$AE$1:$AF$975,2,FALSE),0) -> 0 | X169: =IFERROR(VLOOKUP(E169,Sheet2!$AG$1:$AH$975,2,FALSE),0) -> 0 | Z169: =IFERROR(VLOOKUP(F169,Sheet2!$AA$1:$AB$975,2,FALSE),0) -> 0 | AA169: =IFERROR(VLOOKUP(F169,Sheet2!$AC$1:$AD$975,2,FALSE),0) -> 0 | AB169: =IFERROR(VLOOKUP(F169,Sheet2!$AE$2:$AF$6539,2,FALSE),0) -> 0 | AC169: =IFERROR(VLOOKUP(F169,Sheet2!$AG$2:$AH$6539,2,FALSE),0) -> 0 | AE169: 0 | AF169: 0 | AG169: 0 | AH169: 0 | AI169: 0 | AJ169: =SUM(AE169+AI169) -> 0 | AK169: =SUM(AJ169*O169) -> 0 | AL169: 0 | AM169: 0
A170: GoBros | B170: 46173 | D170: 048323609562 | E170: WIGF2432_125_lod_3 | F170: ZZWIGF2432_125_lod_3 | G170: #N/A | H170: FBA | I170: F2432 | J170: Wigwam Merino Woodland Boot Socks | K170: Loden | L170: X-Large | O170: 9.495 | R170: =IFERROR(VLOOKUP(E170,Sheet6!$A$2:$B$500,2,FALSE),0) -> 0 | S170: =IFERROR(VLOOKUP(E170,Sheet6!$C$2:$D$35017,2,FALSE),0) -> 0 | U170: =IFERROR(VLOOKUP(E170,Sheet2!$AA$1:$AB$975,2,FALSE),0) -> 0 | V170: =IFERROR(VLOOKUP(E170,Sheet2!$AC$1:$AD$975,2,FALSE),0) -> 0 | W170: =IFERROR(VLOOKUP(E170,Sheet2!$AE$1:$AF$975,2,FALSE),0) -> 0 | X170: =IFERROR(VLOOKUP(E170,Sheet2!$AG$1:$AH$975,2,FALSE),0) -> 0 | Z170: =IFERROR(VLOOKUP(F170,Sheet2!$AA$1:$AB$975,2,FALSE),0) -> 1 | AA170: =IFERROR(VLOOKUP(F170,Sheet2!$AC$1:$AD$975,2,FALSE),0) -> 21.99 | AB170: =IFERROR(VLOOKUP(F170,Sheet2!$AE$2:$AF$6539,2,FALSE),0) -> 18 | AC170: =IFERROR(VLOOKUP(F170,Sheet2!$AG$2:$AH$6539,2,FALSE),0) -> 1 | AE170: 0 | AF170: 6 | AG170: 0 | AH170: 0 | AI170: 6 | AJ170: =SUM(AE170+AI170) -> 6 | AK170: =SUM(AJ170*O170) -> 56.97 | AL170: 0 | AM170: 0
A171: GoBros | B171: 46173 | D171: 048323645249 | E171: WIGF2443_238_blu_1 | F171: ZZWIGF2443_238_blu_1 | G171: #N/A | H171: FBA | I171: F2443 | J171: Wigwam Surpass Lightweight Quarter Socks | K171: Blue/Green | L171: Medium | O171: 7.776 | R171: =IFERROR(VLOOKUP(E171,Sheet6!$A$2:$B$500,2,FALSE),0) -> 0 | S171: =IFERROR(VLOOKUP(E171,Sheet6!$C$2:$D$35017,2,FALSE),0) -> 0 | U171: =IFERROR(VLOOKUP(E171,Sheet2!$AA$1:$AB$975,2,FALSE),0) -> 0 | V171: =IFERROR(VLOOKUP(E171,Sheet2!$AC$1:$AD$975,2,FALSE),0) -> 0 | W171: =IFERROR(VLOOKUP(E171,Sheet2!$AE$1:$AF$975,2,FALSE),0) -> 0 | X171: =IFERROR(VLOOKUP(E171,Sheet2!$AG$1:$AH$975,2,FALSE),0) -> 0 | Z171: =IFERROR(VLOOKUP(F171,Sheet2!$AA$1:$AB$975,2,FALSE),0) -> 0 | AA171: =IFERROR(VLOOKUP(F171,Sheet2!$AC$1:$AD$975,2,FALSE),0) -> 0 | AB171: =IFERROR(VLOOKUP(F171,Sheet2!$AE$2:$AF$6539,2,FALSE),0) -> 0 | AC171: =IFERROR(VLOOKUP(F171,Sheet2!$AG$2:$AH$6539,2,FALSE),0) -> 0 | AE171: 0 | AF171: 0 | AG171: 0 | AH171: 0 | AI171: 0 | AJ171: =SUM(AE171+AI171) -> 0 | AK171: =SUM(AJ171*O171) -> 0 | AL171: 0 | AM171: 0
A172: GoBros | B172: 46173 | D172: 048323645270 | E172: WIGF2443_600_red_0 | F172: ZZWIGF2443_600_red_0 | G172: #N/A | H172: FBA | I172: F2443 | J172: Wigwam Surpass Lightweight Quarter Socks | K172: Red/Orange | L172: Small | O172: 7.776 | R172: =IFERROR(VLOOKUP(E172,Sheet6!$A$2:$B$500,2,FALSE),0) -> 0 | S172: =IFERROR(VLOOKUP(E172,Sheet6!$C$2:$D$35017,2,FALSE),0) -> 0 | U172: =IFERROR(VLOOKUP(E172,Sheet2!$AA$1:$AB$975,2,FALSE),0) -> 0 | V172: =IFERROR(VLOOKUP(E172,Sheet2!$AC$1:$AD$975,2,FALSE),0) -> 0 | W172: =IFERROR(VLOOKUP(E172,Sheet2!$AE$1:$AF$975,2,FALSE),0) -> 0 | X172: =IFERROR(VLOOKUP(E172,Sheet2!$AG$1:$AH$975,2,FALSE),0) -> 0 | Z172: =IFERROR(VLOOKUP(F172,Sheet2!$AA$1:$AB$975,2,FALSE),0) -> 0 | AA172: =IFERROR(VLOOKUP(F172,Sheet2!$AC$1:$AD$975,2,FALSE),0) -> 0 | AB172: =IFERROR(VLOOKUP(F172,Sheet2!$AE$2:$AF$6539,2,FALSE),0) -> 0 | AC172: =IFERROR(VLOOKUP(F172,Sheet2!$AG$2:$AH$6539,2,FALSE),0) -> 0 | AE172: 0 | AF172: 0 | AG172: 0 | AH172: 0 | AI172: 0 | AJ172: =SUM(AE172+AI172) -> 0 | AK172: =SUM(AJ172*O172) -> 0 | AL172: 0 | AM172: 0
A173: GoBros | B173: 46173 | D173: 048323645317 | E173: WIGF2443_902_wht_0 | F173: ZZWIGF2443_902_wht_0 | G173: #N/A | H173: FBA | I173: F2443 | J173: Wigwam Surpass Lightweight Quarter Socks | K173: White/Grey | L173: Small | O173: 7.776 | R173: =IFERROR(VLOOKUP(E173,Sheet6!$A$2:$B$500,2,FALSE),0) -> 0 | S173: =IFERROR(VLOOKUP(E173,Sheet6!$C$2:$D$35017,2,FALSE),0) -> 0 | U173: =IFERROR(VLOOKUP(E173,Sheet2!$AA$1:$AB$975,2,FALSE),0) -> 0 | V173: =IFERROR(VLOOKUP(E173,Sheet2!$AC$1:$AD$975,2,FALSE),0) -> 0 | W173: =IFERROR(VLOOKUP(E173,Sheet2!$AE$1:$AF$975,2,FALSE),0) -> 0 | X173: =IFERROR(VLOOKUP(E173,Sheet2!$AG$1:$AH$975,2,FALSE),0) -> 0 | Z173: =IFERROR(VLOOKUP(F173,Sheet2!$AA$1:$AB$975,2,FALSE),0) -> 0 | AA173: =IFERROR(VLOOKUP(F173,Sheet2!$AC$1:$AD$975,2,FALSE),0) -> 0 | AB173: =IFERROR(VLOOKUP(F173,Sheet2!$AE$2:$AF$6539,2,FALSE),0) -> 0 | AC173: =IFERROR(VLOOKUP(F173,Sheet2!$AG$2:$AH$6539,2,FALSE),0) -> 0 | AE173: 0 | AF173: 0 | AG173: 0 | AH173: 0 | AI173: 0 | AJ173: =SUM(AE173+AI173) -> 0 | AK173: =SUM(AJ173*O173) -> 0 | AL173: 0 | AM173: 0
A174: GoBros | B174: 46173 | D174: 048323645409 | E174: WIGF2444_198_blk_0 | F174: ZZWIGF2444_198_blk_0 | G174: #N/A | H174: FBA | I174: F2444 | J174: Wigwam Surpass Lightweight Mid-Crew Socks | K174: Black/Grey | L174: Small | O174: 8.208 | R174: =IFERROR(VLOOKUP(E174,Sheet6!$A$2:$B$500,2,FALSE),0) -> 0 | S174: =IFERROR(VLOOKUP(E174,Sheet6!$C$2:$D$35017,2,FALSE),0) -> 0 | U174: =IFERROR(VLOOKUP(E174,Sheet2!$AA$1:$AB$975,2,FALSE),0) -> 0 | V174: =IFERROR(VLOOKUP(E174,Sheet2!$AC$1:$AD$975,2,FALSE),0) -> 0 | W174: =IFERROR(VLOOKUP(E174,Sheet2!$AE$1:$AF$975,2,FALSE),0) -> 0 | X174: =IFERROR(VLOOKUP(E174,Sheet2!$AG$1:$AH$975,2,FALSE),0) -> 0 | Z174: =IFERROR(VLOOKUP(F174,Sheet2!$AA$1:$AB$975,2,FALSE),0) -> 0 | AA174: =IFERROR(VLOOKUP(F174,Sheet2!$AC$1:$AD$975,2,FALSE),0) -> 0 | AB174: =IFERROR(VLOOKUP(F174,Sheet2!$AE$2:$AF$6539,2,FALSE),0) -> 0 | AC174: =IFERROR(VLOOKUP(F174,Sheet2!$AG$2:$AH$6539,2,FALSE),0) -> 0 | AE174: 0 | AF174: 0 | AG174: 0 | AH174: 0 | AI174: 0 | AJ174: =SUM(AE174+AI174) -> 0 | AK174: =SUM(AJ174*O174) -> 0 | AL174: 0 | AM174: 0
A175: GoBros | B175: 46173 | D175: 048323645522 | E175: WIGF2444_600_red_0 | F175: ZZWIGF2444_600_red_0 | I175: F2444 | J175: Wigwam Surpass Lightweight Mid-Crew Socks | K175: Yucca/Red | L175: Small | O175: 8.208 | R175: =IFERROR(VLOOKUP(E175,Sheet6!$A$2:$B$500,2,FALSE),0) -> 0 | S175: =IFERROR(VLOOKUP(E175,Sheet6!$C$2:$D$35017,2,FALSE),0) -> 0 | U175: =IFERROR(VLOOKUP(E175,Sheet2!$AA$1:$AB$975,2,FALSE),0) -> 0 | V175: =IFERROR(VLOOKUP(E175,Sheet2!$AC$1:$AD$975,2,FALSE),0) -> 0 | W175: =IFERROR(VLOOKUP(E175,Sheet2!$AE$1:$AF$975,2,FALSE),0) -> 0 | X175: =IFERROR(VLOOKUP(E175,Sheet2!$AG$1:$AH$975,2,FALSE),0) -> 0 | Z175: =IFERROR(VLOOKUP(F175,Sheet2!$AA$1:$AB$975,2,FALSE),0) -> 0 | AA175: =IFERROR(VLOOKUP(F175,Sheet2!$AC$1:$AD$975,2,FALSE),0) -> 0 | AB175: =IFERROR(VLOOKUP(F175,Sheet2!$AE$2:$AF$6539,2,FALSE),0) -> 0 | AC175: =IFERROR(VLOOKUP(F175,Sheet2!$AG$2:$AH$6539,2,FALSE),0) -> 0 | AE175: 0 | AF175: 0 | AG175: 0 | AH175: 0 | AI175: 0 | AJ175: =SUM(AE175+AI175) -> 0 | AK175: =SUM(AJ175*O175) -> 0 | AL175: 0 | AM175: 0
A176: GoBros | B176: 46173 | D176: 048323645485 | E176: WIGF2444_902_wht_0 | F176: ZZWIGF2444_902_wht_0 | G176: #N/A | H176: FBM Only | I176: F2444 | J176: Wigwam Surpass Lightweight Mid-Crew Socks | K176: White/Grey | L176: Small | O176: 8.208 | R176: =IFERROR(VLOOKUP(E176,Sheet6!$A$2:$B$500,2,FALSE),0) -> 0 | S176: =IFERROR(VLOOKUP(E176,Sheet6!$C$2:$D$35017,2,FALSE),0) -> 0 | U176: =IFERROR(VLOOKUP(E176,Sheet2!$AA$1:$AB$975,2,FALSE),0) -> 0 | V176: =IFERROR(VLOOKUP(E176,Sheet2!$AC$1:$AD$975,2,FALSE),0) -> 0 | W176: =IFERROR(VLOOKUP(E176,Sheet2!$AE$1:$AF$975,2,FALSE),0) -> 0 | X176: =IFERROR(VLOOKUP(E176,Sheet2!$AG$1:$AH$975,2,FALSE),0) -> 0 | Z176: =IFERROR(VLOOKUP(F176,Sheet2!$AA$1:$AB$975,2,FALSE),0) -> 0 | AA176: =IFERROR(VLOOKUP(F176,Sheet2!$AC$1:$AD$975,2,FALSE),0) -> 0 | AB176: =IFERROR(VLOOKUP(F176,Sheet2!$AE$2:$AF$6539,2,FALSE),0) -> 0 | AC176: =IFERROR(VLOOKUP(F176,Sheet2!$AG$2:$AH$6539,2,FALSE),0) -> 0 | AE176: 0 | AF176: 0 | AG176: 0 | AH176: 0 | AI176: 0 | AJ176: =SUM(AE176+AI176) -> 0 | AK176: =SUM(AJ176*O176) -> 0 | AL176: 0 | AM176: 0
A177: GoBros | B177: 46173 | D177: 048323656306 | E177: WIGF2449_052_blk_3 | F177: ZZWIGF2449_052_blk_3 | G177: #N/A | H177: FBM Only | I177: F2449 | J177: Wigwam Trail Junkie Lightweight Quarter Socks | K177: Black | L177: X-Large | O177: 8.208 | R177: =IFERROR(VLOOKUP(E177,Sheet6!$A$2:$B$500,2,FALSE),0) -> 0 | S177: =IFERROR(VLOOKUP(E177,Sheet6!$C$2:$D$35017,2,FALSE),0) -> 0 | U177: =IFERROR(VLOOKUP(E177,Sheet2!$AA$1:$AB$975,2,FALSE),0) -> 0 | V177: =IFERROR(VLOOKUP(E177,Sheet2!$AC$1:$AD$975,2,FALSE),0) -> 0 | W177: =IFERROR(VLOOKUP(E177,Sheet2!$AE$1:$AF$975,2,FALSE),0) -> 0 | X177: =IFERROR(VLOOKUP(E177,Sheet2!$AG$1:$AH$975,2,FALSE),0) -> 0 | Z177: =IFERROR(VLOOKUP(F177,Sheet2!$AA$1:$AB$975,2,FALSE),0) -> 0 | AA177: =IFERROR(VLOOKUP(F177,Sheet2!$AC$1:$AD$975,2,FALSE),0) -> 0 | AB177: =IFERROR(VLOOKUP(F177,Sheet2!$AE$2:$AF$6539,2,FALSE),0) -> 0 | AC177: =IFERROR(VLOOKUP(F177,Sheet2!$AG$2:$AH$6539,2,FALSE),0) -> 0 | AE177: 0 | AF177: 0 | AG177: 0 | AH177: 0 | AI177: 0 | AJ177: =SUM(AE177+AI177) -> 0 | AK177: =SUM(AJ177*O177) -> 0 | AL177: 0 | AM177: 0
A178: GoBros | B178: 46173 | D178: 048323655637 | E178: WIGF2451_052_blk_3 | F178: ZZWIGF2451_052_blk_3 | G178: #N/A | H178: FBM Only | I178: F2451 | J178: Wigwam Trail Junkie Lightweight Mid Crew Socks | K178: Black | L178: X-Large | O178: 8.64 | R178: =IFERROR(VLOOKUP(E178,Sheet6!$A$2:$B$500,2,FALSE),0) -> 0 | S178: =IFERROR(VLOOKUP(E178,Sheet6!$C$2:$D$35017,2,FALSE),0) -> 0 | U178: =IFERROR(VLOOKUP(E178,Sheet2!$AA$1:$AB$975,2,FALSE),0) -> 0 | V178: =IFERROR(VLOOKUP(E178,Sheet2!$AC$1:$AD$975,2,FALSE),0) -> 0 | W178: =IFERROR(VLOOKUP(E178,Sheet2!$AE$1:$AF$975,2,FALSE),0) -> 0 | X178: =IFERROR(VLOOKUP(E178,Sheet2!$AG$1:$AH$975,2,FALSE),0) -> 0 | Z178: =IFERROR(VLOOKUP(F178,Sheet2!$AA$1:$AB$975,2,FALSE),0) -> 0 | AA178: =IFERROR(VLOOKUP(F178,Sheet2!$AC$1:$AD$975,2,FALSE),0) -> 0 | AB178: =IFERROR(VLOOKUP(F178,Sheet2!$AE$2:$AF$6539,2,FALSE),0) -> 0 | AC178: =IFERROR(VLOOKUP(F178,Sheet2!$AG$2:$AH$6539,2,FALSE),0) -> 0 | AE178: 0 | AF178: 0 | AG178: 0 | AH178: 0 | AI178: 0 | AJ178: =SUM(AE178+AI178) -> 0 | AK178: =SUM(AJ178*O178) -> 0 | AL178: 0 | AM178: 0
...

Sheet Sheet6
A1: Product variant SKU | B1: Net items sold | C1: Product variant SKU | D1: Net sales | H1: Product title | I1: Product variant title | J1: Product variant SKU | K1: Net items sold | L1: Gross sales | M1: Discounts | N1: Returns | O1: Net sales | P1: Taxes | Q1: Total sales
A2: WIGF1019_051_wht_0 | B2: 7 | C2: WIGF1019_051_wht_0 | D2: 105 | H2: Wigwam 7-Footer Extra Tall Socks | I2: One Size Fits Most / White | J2: WIGF1019_051_wht_0 | K2: 7 | L2: 105 | M2: 0 | N2: 0 | O2: 105 | P2: 7.24 | Q2: 112.24
A3: WIGF1054_052_bla_3 | B3: 3 | C3: WIGF1054_052_bla_3 | D3: 39 | H3: Wigwam Volley Midweight Crew Socks | I3: X-Large / Black | J3: WIGF1054_052_bla_3 | K3: 3 | L3: 39 | M3: 0 | N3: 0 | O3: 39 | P3: 1.56 | Q3: 40.56
A4: WIGF1055_051_wht_1 | B4: 12 | C4: WIGF1055_051_wht_1 | D4: 180 | H4: Wigwam King Cotton Heavyweight Crew Socks | I4: Large / White | J4: WIGF1055_051_wht_1 | K4: 12 | L4: 180 | M4: 0 | N4: 0 | O4: 180 | P4: 11.27 | Q4: 191.27
A5: WIGF1055_051_wht_2 | B5: 8 | C5: WIGF1055_051_wht_2 | D5: 117.75 | H5: Wigwam King Cotton Heavyweight Crew Socks | I5: X-Large / White | J5: WIGF1055_051_wht_2 | K5: 8 | L5: 120 | M5: -2.25 | N5: 0 | O5: 117.75 | P5: 4.95 | Q5: 122.7
A6: WIGF1055_052_blk_1 | B6: 9 | C6: WIGF1055_052_blk_1 | D6: 135 | H6: Wigwam King Cotton Heavyweight Crew Socks | I6: Large / Black | J6: WIGF1055_052_blk_1 | K6: 9 | L6: 135 | M6: 0 | N6: 0 | O6: 135 | P6: 8.1 | Q6: 143.1
A7: WIGF1055_052_blk_2 | B7: 3 | C7: WIGF1055_052_blk_2 | D7: 45 | H7: Wigwam King Cotton Heavyweight Crew Socks | I7: X-Large / Black | J7: WIGF1055_052_blk_2 | K7: 3 | L7: 45 | M7: 0 | N7: 0 | O7: 45 | P7: 3.6 | Q7: 48.6
A8: WIGF1057_51_whi_1 | B8: 3 | C8: WIGF1057_51_whi_1 | D8: 36 | H8: Wigwam King Cotton High Heavyweight Socks | I8: Medium / White | J8: WIGF1057_51_whi_1 | K8: 3 | L8: 54 | M8: -18 | N8: 0 | O8: 36 | P8: 0 | Q8: 36
A9: WIGF1057_51_whi_2 | B9: 4 | C9: WIGF1057_51_whi_2 | D9: 72 | H9: Wigwam King Cotton High Heavyweight Socks | I9: Large / White | J9: WIGF1057_51_whi_2 | K9: 4 | L9: 72 | M9: 0 | N9: 0 | O9: 72 | P9: 4.36 | Q9: 76.36
A10: WIGF1057_51_whi_3 | B10: 5 | C10: WIGF1057_51_whi_3 | D10: 90 | H10: Wigwam King Cotton High Heavyweight Socks | I10: X-Large / White | J10: WIGF1057_51_whi_3 | K10: 5 | L10: 90 | M10: 0 | N10: 0 | O10: 90 | P10: 6.76 | Q10: 96.76
A11: WIGF1072_051_wht_1 | B11: 5 | C11: WIGF1072_051_wht_1 | D11: 65.8 | H11: Wigwam Advantage Crew Socks | I11: Large / White | J11: WIGF1072_051_wht_1 | K11: 5 | L11: 70 | M11: -4.2 | N11: 0 | O11: 65.8 | P11: 5.32 | Q11: 71.12
A12: WIGF1086_051_nat_0 | B12: 2 | C12: WIGF1086_051_nat_0 | D12: 44 | H12: Wigwam 625 Wool Crew Socks | I12: Medium / White | J12: WIGF1086_051_nat_0 | K12: 2 | L12: 44 | M12: 0 | N12: 0 | O12: 44 | P12: 0 | Q12: 44
A13: WIGF1086_051_nat_2 | B13: 1 | C13: WIGF1086_051_nat_2 | D13: 22 | H13: Wigwam 625 Wool Crew Socks | I13: X-Large / White | J13: WIGF1086_051_nat_2 | K13: 1 | L13: 22 | M13: 0 | N13: 0 | O13: 22 | P13: 0.96 | Q13: 22.96
... A80: WIGS9020_51_whi_3 | B80: 6 | C80: WIGS9020_51_whi_3 | D80: 204 | H80: Wigwam Super 60 Crew 6-Pack Midweight Cotton Socks | I80: X-Large / White | J80: WIGS9020_51_whi_3 | K80: 6 | L80: 204 | M80: 0 | N80: 0 | O80: 204 | P80: 6.72 | Q80: 210.72
AE107: x

Sheet Sheet2
A1: (Parent) ASIN | B1: (Child) ASIN | C1: Title | D1: SKU | E1: Sessions - Total | F1: Sessions - Total - B2B | G1: Session Percentage - Total | H1: Session Percentage - Total - B2B | I1: Page Views - Total | J1: Page Views - Total - B2B | K1: Page Views Percentage - Total | L1: Page Views Percentage - Total - B2B | M1: Featured Offer (Buy Box) Percentage | N1: Featured Offer (Buy Box) Percentage - B2B | O1: Units Ordered | P1: Units Ordered - B2B | Q1: Unit Session Percentage | R1: Unit Session Percentage - B2B | S1: Ordered Product Sales | T1: Ordered Product Sales - B2B | U1: Total Order Items | V1: Total Order Items - B2B | AA1: SKU | AB1: Units Ordered | AC1: SKU | AD1: Ordered Product Sales | AE1: SKU | AF1: Sessions - Total | AG1: SKU | AH1: Featured Offer (Buy Box) Percentage
A2: B07BRBQ5FP | B2: B000ARG1KQ | C2: Wigwam 7 Footer Athletic Socks, White, One Size | D2: WIGF1019_051_wht_0 | E2: 86 | F2: 2 | G2: 0.0001 | H2: 0.0001 | I2: 123 | J2: 2 | K2: 0.0001 | L2: 0.0001 | M2: 0.1339 | N2: 0 | O2: 5 | P2: 0 | Q2: 0.0581 | R2: 0 | S2: 74.95 | T2: 0 | U2: 3 | V2: 0 | AA2: WIGF1019_051_wht_0 | AB2: 5 | AC2: WIGF1019_051_wht_0 | AD2: 74.95 | AE2: WIGF1019_051_wht_0 | AF2: 86 | AG2: WIGF1019_051_wht_0 | AH2: 0.1339
A3: B00NF6Y9LW | B3: B0019OTSH2 | C3: WigWam Volley Athletic Socks, White, Md | D3: WIGF1054_051_whi_1 | E3: 7 | F3: 0 | G3: 0 | H3: 0 | I3: 11 | J3: 0 | K3: 0 | L3: 0 | M3: 1 | N3: 0 | O3: 5 | P3: 0 | Q3: 0.7143 | R3: 0 | S3: 65 | T3: 0 | U3: 2 | V3: 0 | AA3: WIGF1054_051_whi_1 | AB3: 5 | AC3: WIGF1054_051_whi_1 | AD3: 65 | AE3: WIGF1054_051_whi_1 | AF3: 7 | AG3: WIGF1054_051_whi_1 | AH3: 1
A4: B00NF6Y9LW | B4: B000G7Y0AS | C4: WigWam Volley Athletic Socks, Black, Lg | D4: WIGF1054_052_bla_2 | E4: 11 | F4: 0 | G4: 0 | H4: 0 | I4: 17 | J4: 0 | K4: 0 | L4: 0 | M4: 1 | N4: 0 | O4: 3 | P4: 0 | Q4: 0.2727 | R4: 0 | S4: 39 | T4: 0 | U4: 2 | V4: 0 | AA4: WIGF1054_052_bla_2 | AB4: 3 | AC4: WIGF1054_052_bla_2 | AD4: 39 | AE4: WIGF1054_052_bla_2 | AF4: 11 | AG4: WIGF1054_052_bla_2 | AH4: 1
A5: B00NF6Y9LW | B5: B000V5EE56 | C5: WigWam Volley Athletic Socks, Black, Xl | D5: WIGF1054_052_bla_3 | E5: 2 | F5: 0 | G5: 0 | H5: 0 | I5: 7 | J5: 0 | K5: 0 | L5: 0 | M5: 1 | N5: 0 | O5: 1 | P5: 0 | Q5: 0.5 | R5: 0 | S5: 13 | T5: 0 | U5: 1 | V5: 0 | AA5: WIGF1054_052_bla_3 | AB5: 1 | AC5: WIGF1054_052_bla_3 | AD5: 13 | AE5: WIGF1054_052_bla_3 | AF5: 2 | AG5: WIGF1054_052_bla_3 | AH5: 1
A6: B000TF9LZG | B6: B000TA744G | C6: Wigwam King Cotton Crew F1055 Sock | D6: WIGF1055_051_wht_1 | E6: 271 | F6: 4 | G6: 0.0002 | H6: 0.0002 | I6: 390 | J6: 4 | K6: 0.0002 | L6: 0.0001 | M6: 1 | N6: 1 | O6: 87 | P6: 0 | Q6: 0.321 | R6: 0 | S6: 1304.13 | T6: 0 | U6: 34 | V6: 0 | AA6: WIGF1055_051_wht_1 | AB6: 87 | AC6: WIGF1055_051_wht_1 | AD6: 1304.13 | AE6: WIGF1055_051_wht_1 | AF6: 271 | AG6: WIGF1055_051_wht_1 | AH6: 1
A7: B000TF9LZG | B7: B000TA1SJI | C7: Wigwam King Cotton Heavyweight Crew Socks, White - X-Large | D7: WIGF1055_051_wht_2 | E7: 131 | F7: 1 | G7: 0.0001 | H7: 0 | I7: 177 | J7: 1 | K7: 0.0001 | L7: 0 | M7: 1 | N7: 1 | O7: 46 | P7: 0 | Q7: 0.3511 | R7: 0 | S7: 690 | T7: 0 | U7: 19 | V7: 0 | AA7: WIGF1055_051_wht_2 | AB7: 46 | AC7: WIGF1055_051_wht_2 | AD7: 690 | AE7: WIGF1055_051_wht_2 | AF7: 131 | AG7: WIGF1055_051_wht_2 | AH7: 1
A8: B000TF9LZG | B8: B004QJOC00 | C8: WigWam Men's King Crew Athletic Socks, X-Large Sock , Black | D8: WIGF1055_052_blk_2 | E8: 36 | F8: 0 | G8: 0 | H8: 0 | I8: 52 | J8: 0 | K8: 0 | L8: 0 | M8: 0.4894 | N8: 0 | O8: 7 | P8: 0 | Q8: 0.1944 | R8: 0 | S8: 105 | T8: 0 | U8: 5 | V8: 0 | AA8: WIGF1055_052_blk_2 | AB8: 7 | AC8: WIGF1055_052_blk_2 | AD8: 105 | AE8: WIGF1055_052_blk_2 | AF8: 36 | AG8: WIGF1055_052_blk_2 | AH8: 0.4894
A9: B00NF6Y5N4 | B9: B0088V4SG0 | C9: Wigwam Master F1061 Sock, White - 13 | D9: WIGF1061_051_wht_3 | E9: 20 | F9: 0 | G9: 0 | H9: 0 | I9: 36 | J9: 0 | K9: 0 | L9: 0 | M9: 0.9688 | N9: 0 | O9: 8 | P9: 0 | Q9: 0.4 | R9: 0 | S9: 144 | T9: 0 | U9: 3 | V9: 0 | AA9: WIGF1061_051_wht_3 | AB9: 8 | AC9: WIGF1061_051_wht_3 | AD9: 144 | AE9: WIGF1061_051_wht_3 | AF9: 20 | AG9: WIGF1061_051_wht_3 | AH9: 0.9688
A10: B00NF6XO9A | B10: B000AREBGM | C10: Wigwam Men's Advantage Socks, White, X-Large | D10: WIGF1072_051_wht_2 | E10: 84 | F10: 0 | G10: 0.0001 | H10: 0 | I10: 105 | J10: 0 | K10: 0.0001 | L10: 0 | M10: 0.9902 | N10: 0 | O10: 2 | P10: 0 | Q10: 0.0238 | R10: 0 | S10: 28 | T10: 0 | U10: 2 | V10: 0 | AA10: WIGF1072_051_wht_2 | AB10: 2 | AC10: WIGF1072_051_wht_2 | AD10: 28 | AE10: WIGF1072_051_wht_2 | AF10: 84 | AG10: WIGF1072_051_wht_2 | AH10: 0.9902
A11: B0CL7S1PQQ | B11: B000ARG1KG | C11: Wigwam 625 Light Weight Wool Athletic Socks, White, X-Large | D11: WIGF1086_051_nat_2 | E11: 191 | F11: 2 | G11: 0.0001 | H11: 0.0001 | I11: 298 | J11: 3 | K11: 0.0001 | L11: 0.0001 | M11: 0.3222 | N11: 0 | O11: 4 | P11: 0 | Q11: 0.0209 | R11: 0 | S11: 87.96 | T11: 0 | U11: 3 | V11: 0 | AA11: WIGF1086_051_nat_2 | AB11: 4 | AC11: WIGF1086_051_nat_2 | AD11: 87.96 | AE11: WIGF1086_051_nat_2 | AF11: 191 | AG11: WIGF1086_051_nat_2 | AH11: 0.3222
A12: B07CPGJV5L | B12: B000FCILZE | C12: Wigwam At Work Steel Toe Crew Socks, White/Black - Medium | D12: WIGF1140_731_whi_1 | E12: 16 | F12: 1 | G12: 0 | H12: 0 | I12: 19 | J12: 1 | K12: 0 | L12: 0 | M12: 1 | N12: 0 | O12: 8 | P12: 0 | Q12: 0.5 | R12: 0 | S12: 128 | T12: 0 | U12: 3 | V12: 0 | AA12: WIGF1140_731_whi_1 | AB12: 8 | AC12: WIGF1140_731_whi_1 | AD12: 128 | AE12: WIGF1140_731_whi_1 | AF12: 16 | AG12: WIGF1140_731_whi_1 | AH12: 1
A13: B09C6RG3TW | B13: B000KPHTWW | C13: Wigwam Men's Diabetic Walker Crew Length Sock,White,XL/shoe Size: Men's 12-15 | D13: WIGF1221_051_wht_2 | E13: 18 | F13: 0 | G13: 0 | H13: 0 | I13: 34 | J13: 0 | K13: 0 | L13: 0 | M13: 1 | N13: 0 | O13: 5 | P13: 0 | Q13: 0.2778 | R13: 0 | S13: 70 | T13: 0 | U13: 2 | V13: 0 | AA13: WIGF1221_051_wht_2 | AB13: 5 | AC13: WIGF1221_051_wht_2 | AD13: 70 | AE13: WIGF1221_051_wht_2 | AF13: 18 | AG13: WIGF1221_051_wht_2 | AH13: 1
... A234: B0GKX2WQVX | B234: B008PJBOW6 | C234: Wigwam Super 60 Crew 6 Pack S9020 Sock, White - XL | D234: ZZWIGS9020_51_whi_3 | E234: 75 | F234: 1 | G234: 0 | H234: 0 | I234: 104 | J234: 1 | K234: 0 | L234: 0 | M234: 0.6939 | N234: 0 | O234: 5 | P234: 0 | Q234: 0.0667 | R234: 0 | S234: 169.95 | T234: 0 | U234: 5 | V234: 0 | AA234: ZZWIGS9020_51_whi_3 | AB234: 5 | AC234: ZZWIGS9020_51_whi_3 | AD234: 169.95 | AE234: ZZWIGS9020_51_whi_3 | AF234: 75 | AG234: ZZWIGS9020_51_whi_3 | AH234: 0.6939
